<?xml version="1.0" encoding="utf-8"?>
<Subtitle>
  <Paragraph>
    <Number>1</Number>
    <StartMilliseconds>10642</StartMilliseconds>
    <EndMilliseconds>13023</EndMilliseconds>
    <Text>雨下在绿色的草地上，
Yǔ xiàzài lǜsè de cǎodì shàng,</Text>
  </Paragraph>
  <Paragraph>
    <Number>2</Number>
    <StartMilliseconds>13024</StartMilliseconds>
    <EndMilliseconds>13515</EndMilliseconds>
    <Text>[@雨@]下在绿色的草地上，
[@Yǔ@] xiàzài lǜsè de cǎodì shàng,</Text>
  </Paragraph>
  <Paragraph>
    <Number>3</Number>
    <StartMilliseconds>13516</StartMilliseconds>
    <EndMilliseconds>14483</EndMilliseconds>
    <Text>雨[@下在@]绿色的草地上，
Yǔ [@xiàzài@] lǜsè de cǎodì shàng,</Text>
  </Paragraph>
  <Paragraph>
    <Number>4</Number>
    <StartMilliseconds>14484</StartMilliseconds>
    <EndMilliseconds>15256</EndMilliseconds>
    <Text>雨下在[@绿色@]的草地上，
Yǔ xiàzài [@lǜsè@] de cǎodì shàng,</Text>
  </Paragraph>
  <Paragraph>
    <Number>5</Number>
    <StartMilliseconds>15257</StartMilliseconds>
    <EndMilliseconds>15523</EndMilliseconds>
    <Text>雨下在绿色[@的@]草地上，
Yǔ xiàzài lǜsè [@de@] cǎodì shàng,</Text>
  </Paragraph>
  <Paragraph>
    <Number>6</Number>
    <StartMilliseconds>15524</StartMilliseconds>
    <EndMilliseconds>16348</EndMilliseconds>
    <Text>雨下在绿色的[@草地@]上，
Yǔ xiàzài lǜsè de [@cǎodì@] shàng,</Text>
  </Paragraph>
  <Paragraph>
    <Number>7</Number>
    <StartMilliseconds>16349</StartMilliseconds>
    <EndMilliseconds>16682</EndMilliseconds>
    <Text>雨下在绿色的草地[@上@]，
Yǔ xiàzài lǜsè de cǎodì [@shàng@],</Text>
  </Paragraph>
  <Paragraph>
    <Number>8</Number>
    <StartMilliseconds>16683</StartMilliseconds>
    <EndMilliseconds>17290</EndMilliseconds>
    <Text>雨下在绿色的草地上，
Yǔ xiàzài lǜsè de cǎodì shàng,</Text>
  </Paragraph>
  <Paragraph>
    <Number>9</Number>
    <StartMilliseconds>17291</StartMilliseconds>
    <EndMilliseconds>17807</EndMilliseconds>
    <Text>雨下在树上， 
yǔ xiàzài shù shàng,</Text>
  </Paragraph>
  <Paragraph>
    <Number>10</Number>
    <StartMilliseconds>17808</StartMilliseconds>
    <EndMilliseconds>18323</EndMilliseconds>
    <Text>[@雨@]下在树上， 
[@yǔ@] xiàzài shù shàng,</Text>
  </Paragraph>
  <Paragraph>
    <Number>11</Number>
    <StartMilliseconds>18324</StartMilliseconds>
    <EndMilliseconds>19335</EndMilliseconds>
    <Text>雨[@下在@]树上， 
yǔ [@xiàzài@] shù shàng,</Text>
  </Paragraph>
  <Paragraph>
    <Number>12</Number>
    <StartMilliseconds>19336</StartMilliseconds>
    <EndMilliseconds>19899</EndMilliseconds>
    <Text>雨下在[@树@]上， 
yǔ xiàzài [@shù@] shàng,</Text>
  </Paragraph>
  <Paragraph>
    <Number>13</Number>
    <StartMilliseconds>19900</StartMilliseconds>
    <EndMilliseconds>20268</EndMilliseconds>
    <Text>雨下在树[@上@]， 
yǔ xiàzài shù [@shàng@],</Text>
  </Paragraph>
  <Paragraph>
    <Number>14</Number>
    <StartMilliseconds>20269</StartMilliseconds>
    <EndMilliseconds>22053</EndMilliseconds>
    <Text>雨下在树上， 
yǔ xiàzài shù shàng,</Text>
  </Paragraph>
  <Paragraph>
    <Number>15</Number>
    <StartMilliseconds>22054</StartMilliseconds>
    <EndMilliseconds>22761</EndMilliseconds>
    <Text>雨下在屋顶上，
yǔ xiàzài wūdǐng shàng,</Text>
  </Paragraph>
  <Paragraph>
    <Number>16</Number>
    <StartMilliseconds>22762</StartMilliseconds>
    <EndMilliseconds>23195</EndMilliseconds>
    <Text>[@雨@]下在屋顶上，
[@yǔ@] xiàzài wūdǐng shàng,</Text>
  </Paragraph>
  <Paragraph>
    <Number>17</Number>
    <StartMilliseconds>23196</StartMilliseconds>
    <EndMilliseconds>24218</EndMilliseconds>
    <Text>雨[@下在@]屋顶上，
yǔ [@xiàzài@] wūdǐng shàng,</Text>
  </Paragraph>
  <Paragraph>
    <Number>18</Number>
    <StartMilliseconds>24219</StartMilliseconds>
    <EndMilliseconds>25042</EndMilliseconds>
    <Text>雨下在[@屋顶@]上，
yǔ xiàzài [@wūdǐng@] shàng,</Text>
  </Paragraph>
  <Paragraph>
    <Number>19</Number>
    <StartMilliseconds>25043</StartMilliseconds>
    <EndMilliseconds>25471</EndMilliseconds>
    <Text>雨下在屋顶[@上@]，
yǔ xiàzài wūdǐng [@shàng@],</Text>
  </Paragraph>
  <Paragraph>
    <Number>20</Number>
    <StartMilliseconds>25472</StartMilliseconds>
    <EndMilliseconds>25877</EndMilliseconds>
    <Text>雨下在屋顶上，
yǔ xiàzài wūdǐng shàng,</Text>
  </Paragraph>
  <Paragraph>
    <Number>21</Number>
    <StartMilliseconds>25878</StartMilliseconds>
    <EndMilliseconds>26302</EndMilliseconds>
    <Text>但没有下在我身上。
dàn méiyǒu xiàzài wǒ shēn shàng.</Text>
  </Paragraph>
  <Paragraph>
    <Number>22</Number>
    <StartMilliseconds>26303</StartMilliseconds>
    <EndMilliseconds>26685</EndMilliseconds>
    <Text>[@但@]没有下在我身上。
[@dàn@] méiyǒu xiàzài wǒ shēn shàng.</Text>
  </Paragraph>
  <Paragraph>
    <Number>23</Number>
    <StartMilliseconds>26686</StartMilliseconds>
    <EndMilliseconds>27359</EndMilliseconds>
    <Text>但[@没有@]下在我身上。
dàn [@méiyǒu@] xiàzài wǒ shēn shàng.</Text>
  </Paragraph>
  <Paragraph>
    <Number>24</Number>
    <StartMilliseconds>27360</StartMilliseconds>
    <EndMilliseconds>28303</EndMilliseconds>
    <Text>但没有[@下在@]我身上。
dàn méiyǒu [@xiàzài@] wǒ shēn shàng.</Text>
  </Paragraph>
  <Paragraph>
    <Number>25</Number>
    <StartMilliseconds>28304</StartMilliseconds>
    <EndMilliseconds>28835</EndMilliseconds>
    <Text>但没有下在[@我@]身上。
dàn méiyǒu xiàzài [@wǒ@] shēn shàng.</Text>
  </Paragraph>
  <Paragraph>
    <Number>26</Number>
    <StartMilliseconds>28836</StartMilliseconds>
    <EndMilliseconds>29181</EndMilliseconds>
    <Text>但没有下在我[@身@]上。
dàn méiyǒu xiàzài wǒ [@shēn@] shàng.</Text>
  </Paragraph>
  <Paragraph>
    <Number>27</Number>
    <StartMilliseconds>29182</StartMilliseconds>
    <EndMilliseconds>29537</EndMilliseconds>
    <Text>但没有下在我身[@上@]。
dàn méiyǒu xiàzài wǒ shēn [@shàng@].</Text>
  </Paragraph>
  <Paragraph>
    <Number>28</Number>
    <StartMilliseconds>29538</StartMilliseconds>
    <EndMilliseconds>30856</EndMilliseconds>
    <Text>但没有下在我身上。
dàn méiyǒu xiàzài wǒ shēn shàng.</Text>
  </Paragraph>
  <Paragraph>
    <Number>29</Number>
    <StartMilliseconds>30857</StartMilliseconds>
    <EndMilliseconds>31673</EndMilliseconds>
    <Text>雨下在人行道上，
Yǔ xiàzài rénxíngdào shàng,</Text>
  </Paragraph>
  <Paragraph>
    <Number>30</Number>
    <StartMilliseconds>31674</StartMilliseconds>
    <EndMilliseconds>32219</EndMilliseconds>
    <Text>[@雨@]下在人行道上，
[@Yǔ@] xiàzài rénxíngdào shàng,</Text>
  </Paragraph>
  <Paragraph>
    <Number>31</Number>
    <StartMilliseconds>32220</StartMilliseconds>
    <EndMilliseconds>33134</EndMilliseconds>
    <Text>雨[@下在@]人行道上，
Yǔ [@xiàzài@] rénxíngdào shàng,</Text>
  </Paragraph>
  <Paragraph>
    <Number>32</Number>
    <StartMilliseconds>33135</StartMilliseconds>
    <EndMilliseconds>34422</EndMilliseconds>
    <Text>雨下在[@人行道@]上，
Yǔ xiàzài [@rénxíngdào@] shàng,</Text>
  </Paragraph>
  <Paragraph>
    <Number>33</Number>
    <StartMilliseconds>34423</StartMilliseconds>
    <EndMilliseconds>34782</EndMilliseconds>
    <Text>雨下在人行道[@上@]，
Yǔ xiàzài rénxíngdào [@shàng@],</Text>
  </Paragraph>
  <Paragraph>
    <Number>34</Number>
    <StartMilliseconds>34783</StartMilliseconds>
    <EndMilliseconds>35304</EndMilliseconds>
    <Text>雨下在人行道上，
Yǔ xiàzài rénxíngdào shàng,</Text>
  </Paragraph>
  <Paragraph>
    <Number>35</Number>
    <StartMilliseconds>35312</StartMilliseconds>
    <EndMilliseconds>36414</EndMilliseconds>
    <Text>雨下在篱笆上，
yǔ xiàzài líba shàng,</Text>
  </Paragraph>
  <Paragraph>
    <Number>36</Number>
    <StartMilliseconds>36415</StartMilliseconds>
    <EndMilliseconds>36845</EndMilliseconds>
    <Text>[@雨@]下在篱笆上，
[@yǔ@] xiàzài líba shàng,</Text>
  </Paragraph>
  <Paragraph>
    <Number>37</Number>
    <StartMilliseconds>36846</StartMilliseconds>
    <EndMilliseconds>37838</EndMilliseconds>
    <Text>雨[@下在@]篱笆上，
yǔ [@xiàzài@] líba shàng,</Text>
  </Paragraph>
  <Paragraph>
    <Number>38</Number>
    <StartMilliseconds>37839</StartMilliseconds>
    <EndMilliseconds>38555</EndMilliseconds>
    <Text>雨下在[@篱笆@]上，
yǔ xiàzài [@líba@] shàng,</Text>
  </Paragraph>
  <Paragraph>
    <Number>39</Number>
    <StartMilliseconds>38556</StartMilliseconds>
    <EndMilliseconds>38908</EndMilliseconds>
    <Text>雨下在篱笆[@上@]，
yǔ xiàzài líba [@shàng@],</Text>
  </Paragraph>
  <Paragraph>
    <Number>40</Number>
    <StartMilliseconds>38909</StartMilliseconds>
    <EndMilliseconds>40122</EndMilliseconds>
    <Text>雨下在篱笆上，
yǔ xiàzài líba shàng,</Text>
  </Paragraph>
  <Paragraph>
    <Number>41</Number>
    <StartMilliseconds>40123</StartMilliseconds>
    <EndMilliseconds>41077</EndMilliseconds>
    <Text>雨下在邮箱上，
yǔ xiàzài yóuxiāng shàng,</Text>
  </Paragraph>
  <Paragraph>
    <Number>42</Number>
    <StartMilliseconds>41078</StartMilliseconds>
    <EndMilliseconds>41583</EndMilliseconds>
    <Text>[@雨@]下在邮箱上，
[@yǔ@] xiàzài yóuxiāng shàng,</Text>
  </Paragraph>
  <Paragraph>
    <Number>43</Number>
    <StartMilliseconds>41584</StartMilliseconds>
    <EndMilliseconds>42653</EndMilliseconds>
    <Text>雨[@下在@]邮箱上，
yǔ [@xiàzài@] yóuxiāng shàng,</Text>
  </Paragraph>
  <Paragraph>
    <Number>44</Number>
    <StartMilliseconds>42654</StartMilliseconds>
    <EndMilliseconds>43512</EndMilliseconds>
    <Text>雨下在[@邮箱@]上，
yǔ xiàzài [@yóuxiāng@] shàng,</Text>
  </Paragraph>
  <Paragraph>
    <Number>45</Number>
    <StartMilliseconds>43513</StartMilliseconds>
    <EndMilliseconds>43797</EndMilliseconds>
    <Text>雨下在邮箱[@上@]，
yǔ xiàzài yóuxiāng [@shàng@],</Text>
  </Paragraph>
  <Paragraph>
    <Number>46</Number>
    <StartMilliseconds>43798</StartMilliseconds>
    <EndMilliseconds>44183</EndMilliseconds>
    <Text>雨下在邮箱上，
yǔ xiàzài yóuxiāng shàng,</Text>
  </Paragraph>
  <Paragraph>
    <Number>47</Number>
    <StartMilliseconds>44184</StartMilliseconds>
    <EndMilliseconds>44446</EndMilliseconds>
    <Text>但没有下在我身上。
dàn méiyǒu xiàzài wǒ shēn shàng.</Text>
  </Paragraph>
  <Paragraph>
    <Number>48</Number>
    <StartMilliseconds>44447</StartMilliseconds>
    <EndMilliseconds>45087</EndMilliseconds>
    <Text>[@但@]没有下在我身上。
[@dàn@] méiyǒu xiàzài wǒ shēn shàng.</Text>
  </Paragraph>
  <Paragraph>
    <Number>49</Number>
    <StartMilliseconds>45088</StartMilliseconds>
    <EndMilliseconds>45705</EndMilliseconds>
    <Text>但[@没有@]下在我身上。
dàn [@méiyǒu@] xiàzài wǒ shēn shàng.</Text>
  </Paragraph>
  <Paragraph>
    <Number>50</Number>
    <StartMilliseconds>45706</StartMilliseconds>
    <EndMilliseconds>46540</EndMilliseconds>
    <Text>但没有[@下在@]我身上。
dàn méiyǒu [@xiàzài@] wǒ shēn shàng.</Text>
  </Paragraph>
  <Paragraph>
    <Number>51</Number>
    <StartMilliseconds>46541</StartMilliseconds>
    <EndMilliseconds>47034</EndMilliseconds>
    <Text>但没有下在[@我@]身上。
dàn méiyǒu xiàzài [@wǒ@] shēn shàng.</Text>
  </Paragraph>
  <Paragraph>
    <Number>52</Number>
    <StartMilliseconds>47035</StartMilliseconds>
    <EndMilliseconds>47410</EndMilliseconds>
    <Text>但没有下在我[@身@]上。
dàn méiyǒu xiàzài wǒ [@shēn@] shàng.</Text>
  </Paragraph>
  <Paragraph>
    <Number>53</Number>
    <StartMilliseconds>47411</StartMilliseconds>
    <EndMilliseconds>47743</EndMilliseconds>
    <Text>但没有下在我身[@上@]。
dàn méiyǒu xiàzài wǒ shēn [@shàng@].</Text>
  </Paragraph>
  <Paragraph>
    <Number>54</Number>
    <StartMilliseconds>47744</StartMilliseconds>
    <EndMilliseconds>49244</EndMilliseconds>
    <Text>但没有下在我身上。
dàn méiyǒu xiàzài wǒ shēn shàng.</Text>
  </Paragraph>
  <Paragraph>
    <Number>55</Number>
    <StartMilliseconds>49245</StartMilliseconds>
    <EndMilliseconds>50021</EndMilliseconds>
    <Text>雨下在车道上，
Yǔ xiàzài chēdào shàng,</Text>
  </Paragraph>
  <Paragraph>
    <Number>56</Number>
    <StartMilliseconds>50022</StartMilliseconds>
    <EndMilliseconds>50412</EndMilliseconds>
    <Text>[@雨@]下在车道上，
[@Yǔ@] xiàzài chēdào shàng,</Text>
  </Paragraph>
  <Paragraph>
    <Number>57</Number>
    <StartMilliseconds>50413</StartMilliseconds>
    <EndMilliseconds>51306</EndMilliseconds>
    <Text>雨[@下在@]车道上，
Yǔ [@xiàzài@] chēdào shàng,</Text>
  </Paragraph>
  <Paragraph>
    <Number>58</Number>
    <StartMilliseconds>51307</StartMilliseconds>
    <EndMilliseconds>52156</EndMilliseconds>
    <Text>雨下在[@车道@]上，
Yǔ xiàzài [@chēdào@] shàng,</Text>
  </Paragraph>
  <Paragraph>
    <Number>59</Number>
    <StartMilliseconds>52157</StartMilliseconds>
    <EndMilliseconds>52504</EndMilliseconds>
    <Text>雨下在车道[@上@]，
Yǔ xiàzài chēdào [@shàng@],</Text>
  </Paragraph>
  <Paragraph>
    <Number>60</Number>
    <StartMilliseconds>52505</StartMilliseconds>
    <EndMilliseconds>53402</EndMilliseconds>
    <Text>雨下在车道上，
Yǔ xiàzài chēdào shàng,</Text>
  </Paragraph>
  <Paragraph>
    <Number>61</Number>
    <StartMilliseconds>53403</StartMilliseconds>
    <EndMilliseconds>54409</EndMilliseconds>
    <Text>雨下在车上，
yǔ xiàzài chē shàng,</Text>
  </Paragraph>
  <Paragraph>
    <Number>62</Number>
    <StartMilliseconds>54410</StartMilliseconds>
    <EndMilliseconds>54949</EndMilliseconds>
    <Text>[@雨@]下在车上，
[@yǔ@] xiàzài chē shàng,</Text>
  </Paragraph>
  <Paragraph>
    <Number>63</Number>
    <StartMilliseconds>54950</StartMilliseconds>
    <EndMilliseconds>55827</EndMilliseconds>
    <Text>雨[@下在@]车上，
yǔ [@xiàzài@] chē shàng,</Text>
  </Paragraph>
  <Paragraph>
    <Number>64</Number>
    <StartMilliseconds>55828</StartMilliseconds>
    <EndMilliseconds>56356</EndMilliseconds>
    <Text>雨下在[@车@]上，
yǔ xiàzài [@chē@] shàng,</Text>
  </Paragraph>
  <Paragraph>
    <Number>65</Number>
    <StartMilliseconds>56357</StartMilliseconds>
    <EndMilliseconds>56713</EndMilliseconds>
    <Text>雨下在车[@上@]，
yǔ xiàzài chē [@shàng@],</Text>
  </Paragraph>
  <Paragraph>
    <Number>66</Number>
    <StartMilliseconds>56714</StartMilliseconds>
    <EndMilliseconds>57801</EndMilliseconds>
    <Text>雨下在车上，
yǔ xiàzài chē shàng,</Text>
  </Paragraph>
  <Paragraph>
    <Number>67</Number>
    <StartMilliseconds>57802</StartMilliseconds>
    <EndMilliseconds>58617</EndMilliseconds>
    <Text>雨下在大街上，
yǔ xiàzài dà jiē shàng,</Text>
  </Paragraph>
  <Paragraph>
    <Number>68</Number>
    <StartMilliseconds>58618</StartMilliseconds>
    <EndMilliseconds>59097</EndMilliseconds>
    <Text>[@雨@]下在大街上，
[@yǔ@] xiàzài dà jiē shàng,</Text>
  </Paragraph>
  <Paragraph>
    <Number>69</Number>
    <StartMilliseconds>59098</StartMilliseconds>
    <EndMilliseconds>60085</EndMilliseconds>
    <Text>雨[@下在@]大街上，
yǔ [@xiàzài@] dà jiē shàng,</Text>
  </Paragraph>
  <Paragraph>
    <Number>70</Number>
    <StartMilliseconds>60086</StartMilliseconds>
    <EndMilliseconds>60454</EndMilliseconds>
    <Text>雨下在[@大@]街上，
yǔ xiàzài [@dà@] jiē shàng,</Text>
  </Paragraph>
  <Paragraph>
    <Number>71</Number>
    <StartMilliseconds>60455</StartMilliseconds>
    <EndMilliseconds>60826</EndMilliseconds>
    <Text>雨下在大[@街@]上，
yǔ xiàzài dà [@jiē@] shàng,</Text>
  </Paragraph>
  <Paragraph>
    <Number>72</Number>
    <StartMilliseconds>60827</StartMilliseconds>
    <EndMilliseconds>61094</EndMilliseconds>
    <Text>雨下在大街[@上@]，
yǔ xiàzài dà jiē [@shàng@],</Text>
  </Paragraph>
  <Paragraph>
    <Number>73</Number>
    <StartMilliseconds>61095</StartMilliseconds>
    <EndMilliseconds>61391</EndMilliseconds>
    <Text>雨下在大街上，
yǔ xiàzài dà jiē shàng,</Text>
  </Paragraph>
  <Paragraph>
    <Number>74</Number>
    <StartMilliseconds>61392</StartMilliseconds>
    <EndMilliseconds>61801</EndMilliseconds>
    <Text>但没有下在我身上。
dàn méiyǒu xiàzài wǒ shēn shàng.</Text>
  </Paragraph>
  <Paragraph>
    <Number>75</Number>
    <StartMilliseconds>61802</StartMilliseconds>
    <EndMilliseconds>62340</EndMilliseconds>
    <Text>[@但@]没有下在我身上。
[@dàn@] méiyǒu xiàzài wǒ shēn shàng.</Text>
  </Paragraph>
  <Paragraph>
    <Number>76</Number>
    <StartMilliseconds>62341</StartMilliseconds>
    <EndMilliseconds>62945</EndMilliseconds>
    <Text>但[@没有@]下在我身上。
dàn [@méiyǒu@] xiàzài wǒ shēn shàng.</Text>
  </Paragraph>
  <Paragraph>
    <Number>77</Number>
    <StartMilliseconds>62946</StartMilliseconds>
    <EndMilliseconds>63866</EndMilliseconds>
    <Text>但没有[@下在@]我身上。
dàn méiyǒu [@xiàzài@] wǒ shēn shàng.</Text>
  </Paragraph>
  <Paragraph>
    <Number>78</Number>
    <StartMilliseconds>63867</StartMilliseconds>
    <EndMilliseconds>64370</EndMilliseconds>
    <Text>但没有下在[@我@]身上。
dàn méiyǒu xiàzài [@wǒ@] shēn shàng.</Text>
  </Paragraph>
  <Paragraph>
    <Number>79</Number>
    <StartMilliseconds>64371</StartMilliseconds>
    <EndMilliseconds>64703</EndMilliseconds>
    <Text>但没有下在我[@身@]上。
dàn méiyǒu xiàzài wǒ [@shēn@] shàng.</Text>
  </Paragraph>
  <Paragraph>
    <Number>80</Number>
    <StartMilliseconds>64704</StartMilliseconds>
    <EndMilliseconds>64981</EndMilliseconds>
    <Text>但没有下在我身[@上@]。
dàn méiyǒu xiàzài wǒ shēn [@shàng@].</Text>
  </Paragraph>
  <Paragraph>
    <Number>81</Number>
    <StartMilliseconds>64982</StartMilliseconds>
    <EndMilliseconds>65860</EndMilliseconds>
    <Text>但没有下在我身上。
dàn méiyǒu xiàzài wǒ shēn shàng.</Text>
  </Paragraph>
  <Paragraph>
    <Number>82</Number>
    <StartMilliseconds>65861</StartMilliseconds>
    <EndMilliseconds>66886</EndMilliseconds>
    <Text>雨下在鸟窝上，
Yǔ xiàzài niǎowō shàng,</Text>
  </Paragraph>
  <Paragraph>
    <Number>83</Number>
    <StartMilliseconds>66887</StartMilliseconds>
    <EndMilliseconds>67347</EndMilliseconds>
    <Text>[@雨@]下在鸟窝上，
[@Yǔ@] xiàzài niǎowō shàng,</Text>
  </Paragraph>
  <Paragraph>
    <Number>84</Number>
    <StartMilliseconds>67348</StartMilliseconds>
    <EndMilliseconds>68397</EndMilliseconds>
    <Text>雨[@下在@]鸟窝上，
Yǔ [@xiàzài@] niǎowō shàng,</Text>
  </Paragraph>
  <Paragraph>
    <Number>85</Number>
    <StartMilliseconds>68398</StartMilliseconds>
    <EndMilliseconds>69307</EndMilliseconds>
    <Text>雨下在[@鸟窝@]上，
Yǔ xiàzài [@niǎowō@] shàng,</Text>
  </Paragraph>
  <Paragraph>
    <Number>86</Number>
    <StartMilliseconds>69308</StartMilliseconds>
    <EndMilliseconds>69591</EndMilliseconds>
    <Text>雨下在鸟窝[@上@]，
Yǔ xiàzài niǎowō [@shàng@],</Text>
  </Paragraph>
  <Paragraph>
    <Number>87</Number>
    <StartMilliseconds>69592</StartMilliseconds>
    <EndMilliseconds>70418</EndMilliseconds>
    <Text>雨下在鸟窝上，
Yǔ xiàzài niǎowō shàng,</Text>
  </Paragraph>
  <Paragraph>
    <Number>88</Number>
    <StartMilliseconds>70419</StartMilliseconds>
    <EndMilliseconds>71565</EndMilliseconds>
    <Text>雨下在池塘里，
yǔ xiàzài chítáng li,</Text>
  </Paragraph>
  <Paragraph>
    <Number>89</Number>
    <StartMilliseconds>71566</StartMilliseconds>
    <EndMilliseconds>72043</EndMilliseconds>
    <Text>[@雨@]下在池塘里，
[@yǔ@] xiàzài chítáng li,</Text>
  </Paragraph>
  <Paragraph>
    <Number>90</Number>
    <StartMilliseconds>72044</StartMilliseconds>
    <EndMilliseconds>72995</EndMilliseconds>
    <Text>雨[@下在@]池塘里，
yǔ [@xiàzài@] chítáng li,</Text>
  </Paragraph>
  <Paragraph>
    <Number>91</Number>
    <StartMilliseconds>72996</StartMilliseconds>
    <EndMilliseconds>73819</EndMilliseconds>
    <Text>雨下在[@池塘@]里，
yǔ xiàzài [@chítáng@] li,</Text>
  </Paragraph>
  <Paragraph>
    <Number>92</Number>
    <StartMilliseconds>73820</StartMilliseconds>
    <EndMilliseconds>74115</EndMilliseconds>
    <Text>雨下在池塘[@里@]，
yǔ xiàzài chítáng [@li@],</Text>
  </Paragraph>
  <Paragraph>
    <Number>93</Number>
    <StartMilliseconds>74116</StartMilliseconds>
    <EndMilliseconds>75468</EndMilliseconds>
    <Text>雨下在池塘里，
yǔ xiàzài chítáng li,</Text>
  </Paragraph>
  <Paragraph>
    <Number>94</Number>
    <StartMilliseconds>75469</StartMilliseconds>
    <EndMilliseconds>76366</EndMilliseconds>
    <Text>雨下在狗窝上，
yǔ xiàzài gǒuwō shàng,</Text>
  </Paragraph>
  <Paragraph>
    <Number>95</Number>
    <StartMilliseconds>76367</StartMilliseconds>
    <EndMilliseconds>76928</EndMilliseconds>
    <Text>[@雨@]下在狗窝上，
[@yǔ@] xiàzài gǒuwō shàng,</Text>
  </Paragraph>
  <Paragraph>
    <Number>96</Number>
    <StartMilliseconds>76929</StartMilliseconds>
    <EndMilliseconds>77936</EndMilliseconds>
    <Text>雨[@下在@]狗窝上，
yǔ [@xiàzài@] gǒuwō shàng,</Text>
  </Paragraph>
  <Paragraph>
    <Number>97</Number>
    <StartMilliseconds>77937</StartMilliseconds>
    <EndMilliseconds>78728</EndMilliseconds>
    <Text>雨下在[@狗窝@]上，
yǔ xiàzài [@gǒuwō@] shàng,</Text>
  </Paragraph>
  <Paragraph>
    <Number>98</Number>
    <StartMilliseconds>78729</StartMilliseconds>
    <EndMilliseconds>78984</EndMilliseconds>
    <Text>雨下在狗窝[@上@]，
yǔ xiàzài gǒuwō [@shàng@],</Text>
  </Paragraph>
  <Paragraph>
    <Number>99</Number>
    <StartMilliseconds>78985</StartMilliseconds>
    <EndMilliseconds>79204</EndMilliseconds>
    <Text>雨下在狗窝上，
yǔ xiàzài gǒuwō shàng,</Text>
  </Paragraph>
  <Paragraph>
    <Number>100</Number>
    <StartMilliseconds>79205</StartMilliseconds>
    <EndMilliseconds>79504</EndMilliseconds>
    <Text>但没有下在我身上。
dàn méiyǒu xiàzài wǒ shēn shàng.</Text>
  </Paragraph>
  <Paragraph>
    <Number>101</Number>
    <StartMilliseconds>79505</StartMilliseconds>
    <EndMilliseconds>79949</EndMilliseconds>
    <Text>[@但@]没有下在我身上。
[@dàn@] méiyǒu xiàzài wǒ shēn shàng.</Text>
  </Paragraph>
  <Paragraph>
    <Number>102</Number>
    <StartMilliseconds>79950</StartMilliseconds>
    <EndMilliseconds>80569</EndMilliseconds>
    <Text>但[@没有@]下在我身上。
dàn [@méiyǒu@] xiàzài wǒ shēn shàng.</Text>
  </Paragraph>
  <Paragraph>
    <Number>103</Number>
    <StartMilliseconds>80570</StartMilliseconds>
    <EndMilliseconds>81508</EndMilliseconds>
    <Text>但没有[@下在@]我身上。
dàn méiyǒu [@xiàzài@] wǒ shēn shàng.</Text>
  </Paragraph>
  <Paragraph>
    <Number>104</Number>
    <StartMilliseconds>81509</StartMilliseconds>
    <EndMilliseconds>81929</EndMilliseconds>
    <Text>但没有下在[@我@]身上。
dàn méiyǒu xiàzài [@wǒ@] shēn shàng.</Text>
  </Paragraph>
  <Paragraph>
    <Number>105</Number>
    <StartMilliseconds>81930</StartMilliseconds>
    <EndMilliseconds>82334</EndMilliseconds>
    <Text>但没有下在我[@身@]上。
dàn méiyǒu xiàzài wǒ [@shēn@] shàng.</Text>
  </Paragraph>
  <Paragraph>
    <Number>106</Number>
    <StartMilliseconds>82335</StartMilliseconds>
    <EndMilliseconds>82643</EndMilliseconds>
    <Text>但没有下在我身[@上@]。
dàn méiyǒu xiàzài wǒ shēn [@shàng@].</Text>
  </Paragraph>
  <Paragraph>
    <Number>107</Number>
    <StartMilliseconds>82644</StartMilliseconds>
    <EndMilliseconds>86063</EndMilliseconds>
    <Text>但没有下在我身上。
dàn méiyǒu xiàzài wǒ shēn shàng.</Text>
  </Paragraph>
</Subtitle>