<?xml version="1.0" encoding="utf-8"?>
<Subtitle>
  <Paragraph>
    <Number>1</Number>
    <StartMilliseconds>11251</StartMilliseconds>
    <EndMilliseconds>22191</EndMilliseconds>
    <Text>“我还是很饿。” 大猪拍着肚子抱怨着。</Text>
  </Paragraph>
  <Paragraph>
    <Number>2</Number>
    <StartMilliseconds>22192</StartMilliseconds>
    <EndMilliseconds>27684</EndMilliseconds>
    <Text>“这是一头会说话的猪。” 罗西小声对史密斯侦探说。</Text>
  </Paragraph>
  <Paragraph>
    <Number>3</Number>
    <StartMilliseconds>27684</StartMilliseconds>
    <EndMilliseconds>31933</EndMilliseconds>
    <Text>“它拿着一个耙子。” 史密斯侦探说。</Text>
  </Paragraph>
  <Paragraph>
    <Number>4</Number>
    <StartMilliseconds>31933</StartMilliseconds>
    <EndMilliseconds>38557</EndMilliseconds>
    <Text>面包店的主人跑出来大喊：“你毁了我的面包店！”</Text>
  </Paragraph>
  <Paragraph>
    <Number>5</Number>
    <StartMilliseconds>38557</StartMilliseconds>
    <EndMilliseconds>45475</EndMilliseconds>
    <Text>“哼！” 大猪走开了。</Text>
  </Paragraph>
  <Paragraph>
    <Number>6</Number>
    <StartMilliseconds>45475</StartMilliseconds>
    <EndMilliseconds>48587</EndMilliseconds>
    <Text>“站住！” 罗西大喊。</Text>
  </Paragraph>
  <Paragraph>
    <Number>7</Number>
    <StartMilliseconds>48587</StartMilliseconds>
    <EndMilliseconds>53105</EndMilliseconds>
    <Text>大猪哼了一声：“不！”</Text>
  </Paragraph>
  <Paragraph>
    <Number>8</Number>
    <StartMilliseconds>53105</StartMilliseconds>
    <EndMilliseconds>57565</EndMilliseconds>
    <Text>咻！罗西的眼睛发出激光，打中了大猪的脸。</Text>
  </Paragraph>
  <Paragraph>
    <Number>9</Number>
    <StartMilliseconds>57565</StartMilliseconds>
    <EndMilliseconds>62745</EndMilliseconds>
    <Text>“哎呀！你是怎么做到的？” 大猪揉着脸问。</Text>
  </Paragraph>
  <Paragraph>
    <Number>10</Number>
    <StartMilliseconds>62745</StartMilliseconds>
    <EndMilliseconds>66267</EndMilliseconds>
    <Text>“我有超能力！” 罗西飞起来撞向大猪，</Text>
  </Paragraph>
  <Paragraph>
    <Number>11</Number>
    <StartMilliseconds>66267</StartMilliseconds>
    <EndMilliseconds>68855</EndMilliseconds>
    <Text>他们滚过人行道。</Text>
  </Paragraph>
  <Paragraph>
    <Number>12</Number>
    <StartMilliseconds>68855</StartMilliseconds>
    <EndMilliseconds>71148</EndMilliseconds>
    <Text>人们都跳开了。</Text>
  </Paragraph>
  <Paragraph>
    <Number>13</Number>
    <StartMilliseconds>71148</StartMilliseconds>
    <EndMilliseconds>76685</EndMilliseconds>
    <Text>大猪跳起来，挥着耙子：“你是谁？”</Text>
  </Paragraph>
  <Paragraph>
    <Number>14</Number>
    <StartMilliseconds>76685</StartMilliseconds>
    <EndMilliseconds>81572</EndMilliseconds>
    <Text>“所有的坏人都知道我是谁。” 罗西说着避开了耙子。</Text>
  </Paragraph>
  <Paragraph>
    <Number>15</Number>
    <StartMilliseconds>81572</StartMilliseconds>
    <EndMilliseconds>85488</EndMilliseconds>
    <Text>咻！她的眼睛又发出激光。</Text>
  </Paragraph>
  <Paragraph>
    <Number>16</Number>
    <StartMilliseconds>85488</StartMilliseconds>
    <EndMilliseconds>93256</EndMilliseconds>
    <Text>大猪用耙子挡住激光：“可我不是坏人，我是猪八戒。”</Text>
  </Paragraph>
  <Paragraph>
    <Number>17</Number>
    <StartMilliseconds>93256</StartMilliseconds>
    <EndMilliseconds>98948</EndMilliseconds>
    <Text>“哦，我是火箭女孩儿，一个强大的超级英雄！”</Text>
  </Paragraph>
  <Paragraph>
    <Number>18</Number>
    <StartMilliseconds>98948</StartMilliseconds>
    <EndMilliseconds>102277</EndMilliseconds>
    <Text>罗西说着，冲向八戒。</Text>
  </Paragraph>
  <Paragraph>
    <Number>19</Number>
    <StartMilliseconds>102277</StartMilliseconds>
    <EndMilliseconds>106409</EndMilliseconds>
    <Text>八戒挺起胸膛：“我是一个厉害的神仙！”</Text>
  </Paragraph>
  <Paragraph>
    <Number>20</Number>
    <StartMilliseconds>106409</StartMilliseconds>
    <EndMilliseconds>111230</EndMilliseconds>
    <Text>他举起耙子准备攻击，但是罗西重重地撞向他。</Text>
  </Paragraph>
  <Paragraph>
    <Number>21</Number>
    <StartMilliseconds>111230</StartMilliseconds>
    <EndMilliseconds>116279</EndMilliseconds>
    <Text>砰！八戒向后飞去。</Text>
  </Paragraph>
  <Paragraph>
    <Number>22</Number>
    <StartMilliseconds>116279</StartMilliseconds>
    <EndMilliseconds>121465</EndMilliseconds>
    <Text>“小心！” 一个骑自行车的女人急忙停下。</Text>
  </Paragraph>
  <Paragraph>
    <Number>23</Number>
    <StartMilliseconds>121465</StartMilliseconds>
    <EndMilliseconds>124307</EndMilliseconds>
    <Text>砰！八戒撞在消防栓上。</Text>
  </Paragraph>
  <Paragraph>
    <Number>24</Number>
    <StartMilliseconds>124307</StartMilliseconds>
    <EndMilliseconds>131084</EndMilliseconds>
    <Text>水喷了出来，把出租车推向一个花架。</Text>
  </Paragraph>
  <Paragraph>
    <Number>25</Number>
    <StartMilliseconds>131084</StartMilliseconds>
    <EndMilliseconds>135695</EndMilliseconds>
    <Text>当罗西去帮助出租车司机时，八戒挠了挠头。</Text>
  </Paragraph>
  <Paragraph>
    <Number>26</Number>
    <StartMilliseconds>135695</StartMilliseconds>
    <EndMilliseconds>141600</EndMilliseconds>
    <Text>“我还是跑吧。” 他想，“这个人跟神仙一样厉害。”</Text>
  </Paragraph>
  <Paragraph>
    <Number>27</Number>
    <StartMilliseconds>141600</StartMilliseconds>
    <EndMilliseconds>146000</EndMilliseconds>
    <Text>八戒念了句咒语。</Text>
  </Paragraph>
  <Paragraph>
    <Number>28</Number>
    <StartMilliseconds>146000</StartMilliseconds>
    <EndMilliseconds>152355</EndMilliseconds>
    <Text>他跳上一朵云，突然一股香味飘了过来。</Text>
  </Paragraph>
  <Paragraph>
    <Number>29</Number>
    <StartMilliseconds>152355</StartMilliseconds>
    <EndMilliseconds>156284</EndMilliseconds>
    <Text>“什么吃的这么香？” 他嘀咕着。</Text>
  </Paragraph>
  <Paragraph>
    <Number>30</Number>
    <StartMilliseconds>156284</StartMilliseconds>
    <EndMilliseconds>162480</EndMilliseconds>
    <Text>八戒闻着香味，飞向远处的一座大楼。</Text>
  </Paragraph>
  <Paragraph>
    <Number>31</Number>
    <StartMilliseconds>162480</StartMilliseconds>
    <EndMilliseconds>168856</EndMilliseconds>
    <Text>“猪八戒去哪儿了？” 罗西嘀咕着看向四周。</Text>
  </Paragraph>
  <Paragraph>
    <Number>32</Number>
    <StartMilliseconds>168856</StartMilliseconds>
    <EndMilliseconds>174247</EndMilliseconds>
    <Text>“那头大猪驾着云跑了。” 史密斯侦探匆匆跑过来说。</Text>
  </Paragraph>
  <Paragraph>
    <Number>33</Number>
    <StartMilliseconds>174247</StartMilliseconds>
    <EndMilliseconds>179745</EndMilliseconds>
    <Text>罗西睁大了眼睛：“他会飞？飞去哪边了？”</Text>
  </Paragraph>
  <Paragraph>
    <Number>34</Number>
    <StartMilliseconds>179745</StartMilliseconds>
    <EndMilliseconds>184948</EndMilliseconds>
    <Text>“那边。” 史密斯侦探用手指着美罗城小学的方向说。</Text>
  </Paragraph>
  <Paragraph>
    <Number>35</Number>
    <StartMilliseconds>184948</StartMilliseconds>
    <EndMilliseconds>189853</EndMilliseconds>
    <Text>罗西飞得很快，她看到八戒落在了学校门口。</Text>
  </Paragraph>
  <Paragraph>
    <Number>36</Number>
    <StartMilliseconds>189853</StartMilliseconds>
    <EndMilliseconds>193071</EndMilliseconds>
    <Text>罗西落在了八戒前面。</Text>
  </Paragraph>
  <Paragraph>
    <Number>37</Number>
    <StartMilliseconds>193071</StartMilliseconds>
    <EndMilliseconds>199464</EndMilliseconds>
    <Text>八戒来回挥动着耙子：“别烦我！”</Text>
  </Paragraph>
  <Paragraph>
    <Number>38</Number>
    <StartMilliseconds>199464</StartMilliseconds>
    <EndMilliseconds>202083</EndMilliseconds>
    <Text>罗西抓住了耙子。</Text>
  </Paragraph>
  <Paragraph>
    <Number>39</Number>
    <StartMilliseconds>202083</StartMilliseconds>
    <EndMilliseconds>204020</EndMilliseconds>
    <Text>“看！” 玛拉说，</Text>
  </Paragraph>
  <Paragraph>
    <Number>40</Number>
    <StartMilliseconds>204020</StartMilliseconds>
    <EndMilliseconds>208140</EndMilliseconds>
    <Text>“那是火箭女孩儿！她正在和一头猪打架！”</Text>
  </Paragraph>
  <Paragraph>
    <Number>41</Number>
    <StartMilliseconds>208140</StartMilliseconds>
    <EndMilliseconds>210951</EndMilliseconds>
    <Text>罗西的朋友们跑到窗边。</Text>
  </Paragraph>
  <Paragraph>
    <Number>42</Number>
    <StartMilliseconds>210951</StartMilliseconds>
    <EndMilliseconds>214987</EndMilliseconds>
    <Text>“放开我的耙子！” 八戒大喊。</Text>
  </Paragraph>
  <Paragraph>
    <Number>43</Number>
    <StartMilliseconds>214987</StartMilliseconds>
    <EndMilliseconds>219039</EndMilliseconds>
    <Text>“不！” 罗西从他手中抢过耙子。</Text>
  </Paragraph>
  <Paragraph>
    <Number>44</Number>
    <StartMilliseconds>219039</StartMilliseconds>
    <EndMilliseconds>223706</EndMilliseconds>
    <Text>“加油，火箭女孩儿！” 特勒尔挥着拳头大喊。</Text>
  </Paragraph>
  <Paragraph>
    <Number>45</Number>
    <StartMilliseconds>223706</StartMilliseconds>
    <EndMilliseconds>226659</EndMilliseconds>
    <Text>八戒跺着脚向罗西走去，</Text>
  </Paragraph>
  <Paragraph>
    <Number>46</Number>
    <StartMilliseconds>226659</StartMilliseconds>
    <EndMilliseconds>237775</EndMilliseconds>
    <Text>但他突然停下来，然后弯下腰开始喘气。</Text>
  </Paragraph>
  <Paragraph>
    <Number>47</Number>
    <StartMilliseconds>237775</StartMilliseconds>
    <EndMilliseconds>243191</EndMilliseconds>
    <Text>罗西挠了挠头：“呃……你在做什么？”</Text>
  </Paragraph>
  <Paragraph>
    <Number>48</Number>
    <StartMilliseconds>243191</StartMilliseconds>
    <EndMilliseconds>245959</EndMilliseconds>
    <Text>“休息。” 八戒回答。</Text>
  </Paragraph>
  <Paragraph>
    <Number>49</Number>
    <StartMilliseconds>245959</StartMilliseconds>
    <EndMilliseconds>250107</EndMilliseconds>
    <Text>罗西张大了嘴巴：“什么？”</Text>
  </Paragraph>
  <Paragraph>
    <Number>50</Number>
    <StartMilliseconds>250107</StartMilliseconds>
    <EndMilliseconds>253279</EndMilliseconds>
    <Text>“我说我累了！” 八戒大喊，</Text>
  </Paragraph>
  <Paragraph>
    <Number>51</Number>
    <StartMilliseconds>253279</StartMilliseconds>
    <EndMilliseconds>259410</EndMilliseconds>
    <Text>“而且我……嗝！我吃多了。”</Text>
  </Paragraph>
  <Paragraph>
    <Number>52</Number>
    <StartMilliseconds>259410</StartMilliseconds>
    <EndMilliseconds>263600</EndMilliseconds>
    <Text>“你被逮捕了，猪八戒。” 罗西说。</Text>
  </Paragraph>
  <Paragraph>
    <Number>53</Number>
    <StartMilliseconds>263600</StartMilliseconds>
    <EndMilliseconds>268924</EndMilliseconds>
    <Text>八戒突然从地上拔起一个标志牌扔向罗西。</Text>
  </Paragraph>
  <Paragraph>
    <Number>54</Number>
    <StartMilliseconds>268924</StartMilliseconds>
    <EndMilliseconds>273391</EndMilliseconds>
    <Text>罗西低头躲开了，标志牌砸向一辆路过的卡车。</Text>
  </Paragraph>
  <Paragraph>
    <Number>55</Number>
    <StartMilliseconds>273391</StartMilliseconds>
    <EndMilliseconds>277265</EndMilliseconds>
    <Text>“啊！” 卡车被撞进了灌木丛。</Text>
  </Paragraph>
  <Paragraph>
    <Number>56</Number>
    <StartMilliseconds>277265</StartMilliseconds>
    <EndMilliseconds>280815</EndMilliseconds>
    <Text>罗西去帮助司机。</Text>
  </Paragraph>
  <Paragraph>
    <Number>57</Number>
    <StartMilliseconds>280815</StartMilliseconds>
    <EndMilliseconds>284829</EndMilliseconds>
    <Text>她回来的时候，八戒已经不见了。</Text>
  </Paragraph>
  <Paragraph>
    <Number>58</Number>
    <StartMilliseconds>284829</StartMilliseconds>
    <EndMilliseconds>294056</EndMilliseconds>
    <Text>罗西用超级听力听到了八戒的声音。</Text>
  </Paragraph>
  <Paragraph>
    <Number>59</Number>
    <StartMilliseconds>294056</StartMilliseconds>
    <EndMilliseconds>297077</EndMilliseconds>
    <Text>她顺着声音找到了学校的设备室。</Text>
  </Paragraph>
  <Paragraph>
    <Number>60</Number>
    <StartMilliseconds>297077</StartMilliseconds>
    <EndMilliseconds>304577</EndMilliseconds>
    <Text>罗西打开门，她看到八戒正躺在健身垫上呼呼大睡。</Text>
  </Paragraph>
  <Paragraph>
    <Number>61</Number>
    <StartMilliseconds>304577</StartMilliseconds>
    <EndMilliseconds>310023</EndMilliseconds>
    <Text>罗西慢慢地、悄悄地把八戒举起来，</Text>
  </Paragraph>
  <Paragraph>
    <Number>62</Number>
    <StartMilliseconds>310023</StartMilliseconds>
    <EndMilliseconds>315769</EndMilliseconds>
    <Text>然后把他送进了监狱。</Text>
  </Paragraph>
</Subtitle>