<?xml version="1.0" encoding="utf-8"?>
<Subtitle>
  <Paragraph>
    <Number>1</Number>
    <StartMilliseconds>9475</StartMilliseconds>
    <EndMilliseconds>11592</EndMilliseconds>
    <Text>"Ò, bù!" Tútu shuō.
“哦，不！”涂涂说。</Text>
  </Paragraph>
  <Paragraph>
    <Number>2</Number>
    <StartMilliseconds>11592</StartMilliseconds>
    <EndMilliseconds>11918</EndMilliseconds>
    <Text>"[@Ò@], bù!" Tútu shuō.
“[@哦@]，不！”涂涂说。</Text>
  </Paragraph>
  <Paragraph>
    <Number>3</Number>
    <StartMilliseconds>11918</StartMilliseconds>
    <EndMilliseconds>13019</EndMilliseconds>
    <Text>"Ò, [@bù@]!" Tútu shuō.
“哦，[@不@]！”涂涂说。</Text>
  </Paragraph>
  <Paragraph>
    <Number>4</Number>
    <StartMilliseconds>13019</StartMilliseconds>
    <EndMilliseconds>13437</EndMilliseconds>
    <Text>"Ò, bù!" [@Tútu@] shuō.
“哦，不！”[@涂涂@]说。</Text>
  </Paragraph>
  <Paragraph>
    <Number>5</Number>
    <StartMilliseconds>13437</StartMilliseconds>
    <EndMilliseconds>14118</EndMilliseconds>
    <Text>"Ò, bù!" Tútu [@shuō@].
“哦，不！”涂涂[@说@]。</Text>
  </Paragraph>
  <Paragraph>
    <Number>6</Number>
    <StartMilliseconds>14118</StartMilliseconds>
    <EndMilliseconds>14331</EndMilliseconds>
    <Text>"Ò, bù!" Tútu shuō.
“哦，不！”涂涂说。</Text>
  </Paragraph>
  <Paragraph>
    <Number>7</Number>
    <StartMilliseconds>14331</StartMilliseconds>
    <EndMilliseconds>14766</EndMilliseconds>
    <Text>Tā kànzhe dǎoxià de shù.
他看着倒下的树。</Text>
  </Paragraph>
  <Paragraph>
    <Number>8</Number>
    <StartMilliseconds>14766</StartMilliseconds>
    <EndMilliseconds>15220</EndMilliseconds>
    <Text>[@Tā@] kànzhe dǎoxià de shù.
[@他@]看着倒下的树。</Text>
  </Paragraph>
  <Paragraph>
    <Number>9</Number>
    <StartMilliseconds>15220</StartMilliseconds>
    <EndMilliseconds>15645</EndMilliseconds>
    <Text>Tā [@kànzhe@] dǎoxià de shù.
他[@看着@]倒下的树。</Text>
  </Paragraph>
  <Paragraph>
    <Number>10</Number>
    <StartMilliseconds>15645</StartMilliseconds>
    <EndMilliseconds>16119</EndMilliseconds>
    <Text>Tā kànzhe [@dǎoxià@] de shù.
他看着[@倒下@]的树。</Text>
  </Paragraph>
  <Paragraph>
    <Number>11</Number>
    <StartMilliseconds>16119</StartMilliseconds>
    <EndMilliseconds>16316</EndMilliseconds>
    <Text>Tā kànzhe dǎoxià [@de@] shù.
他看着倒下[@的@]树。</Text>
  </Paragraph>
  <Paragraph>
    <Number>12</Number>
    <StartMilliseconds>16316</StartMilliseconds>
    <EndMilliseconds>16885</EndMilliseconds>
    <Text>Tā kànzhe dǎoxià de [@shù@].
他看着倒下的[@树@]。</Text>
  </Paragraph>
  <Paragraph>
    <Number>13</Number>
    <StartMilliseconds>16885</StartMilliseconds>
    <EndMilliseconds>19333</EndMilliseconds>
    <Text>Tā kànzhe dǎoxià de shù.
他看着倒下的树。</Text>
  </Paragraph>
  <Paragraph>
    <Number>14</Number>
    <StartMilliseconds>19333</StartMilliseconds>
    <EndMilliseconds>20609</EndMilliseconds>
    <Text>"Xiànzài, wǒmen bù néng wánr le."
“现在，我们不能玩儿了。”</Text>
  </Paragraph>
  <Paragraph>
    <Number>15</Number>
    <StartMilliseconds>20609</StartMilliseconds>
    <EndMilliseconds>21874</EndMilliseconds>
    <Text>"[@Xiànzài@], wǒmen bù néng wánr le."
“[@现在@]，我们不能玩儿了。”</Text>
  </Paragraph>
  <Paragraph>
    <Number>16</Number>
    <StartMilliseconds>21874</StartMilliseconds>
    <EndMilliseconds>22402</EndMilliseconds>
    <Text>"Xiànzài, [@wǒmen@] bù néng wánr le."
“现在，[@我们@]不能玩儿了。”</Text>
  </Paragraph>
  <Paragraph>
    <Number>17</Number>
    <StartMilliseconds>22402</StartMilliseconds>
    <EndMilliseconds>22616</EndMilliseconds>
    <Text>"Xiànzài, wǒmen [@bù@] néng wánr le."
“现在，我们[@不@]能玩儿了。”</Text>
  </Paragraph>
  <Paragraph>
    <Number>18</Number>
    <StartMilliseconds>22616</StartMilliseconds>
    <EndMilliseconds>22772</EndMilliseconds>
    <Text>"Xiànzài, wǒmen bù [@néng@] wánr le."
“现在，我们不[@能@]玩儿了。”</Text>
  </Paragraph>
  <Paragraph>
    <Number>19</Number>
    <StartMilliseconds>22772</StartMilliseconds>
    <EndMilliseconds>23186</EndMilliseconds>
    <Text>"Xiànzài, wǒmen bù néng [@wánr@] le."
“现在，我们不能[@玩儿@]了。”</Text>
  </Paragraph>
  <Paragraph>
    <Number>20</Number>
    <StartMilliseconds>23186</StartMilliseconds>
    <EndMilliseconds>23952</EndMilliseconds>
    <Text>"Xiànzài, wǒmen bù néng wánr [@le@]."
“现在，我们不能玩儿[@了@]。”</Text>
  </Paragraph>
  <Paragraph>
    <Number>21</Number>
    <StartMilliseconds>23952</StartMilliseconds>
    <EndMilliseconds>28336</EndMilliseconds>
    <Text>"Xiànzài, wǒmen bù néng wánr le."
“现在，我们不能玩儿了。”</Text>
  </Paragraph>
  <Paragraph>
    <Number>22</Number>
    <StartMilliseconds>28336</StartMilliseconds>
    <EndMilliseconds>29831</EndMilliseconds>
    <Text>Duōduo bǎ shǒu shēnjìn bāo li.
多多把手伸进包里。</Text>
  </Paragraph>
  <Paragraph>
    <Number>23</Number>
    <StartMilliseconds>29831</StartMilliseconds>
    <EndMilliseconds>30446</EndMilliseconds>
    <Text>[@Duōduo@] bǎ shǒu shēnjìn bāo li.
[@多多@]把手伸进包里。</Text>
  </Paragraph>
  <Paragraph>
    <Number>24</Number>
    <StartMilliseconds>30446</StartMilliseconds>
    <EndMilliseconds>30651</EndMilliseconds>
    <Text>Duōduo [@bǎ@] shǒu shēnjìn bāo li.
多多[@把@]手伸进包里。</Text>
  </Paragraph>
  <Paragraph>
    <Number>25</Number>
    <StartMilliseconds>30651</StartMilliseconds>
    <EndMilliseconds>31009</EndMilliseconds>
    <Text>Duōduo bǎ [@shǒu@] shēnjìn bāo li.
多多把[@手@]伸进包里。</Text>
  </Paragraph>
  <Paragraph>
    <Number>26</Number>
    <StartMilliseconds>31009</StartMilliseconds>
    <EndMilliseconds>31362</EndMilliseconds>
    <Text>Duōduo bǎ shǒu [@shēnjìn@] bāo li.
多多把手[@伸进@]包里。</Text>
  </Paragraph>
  <Paragraph>
    <Number>27</Number>
    <StartMilliseconds>31362</StartMilliseconds>
    <EndMilliseconds>31642</EndMilliseconds>
    <Text>Duōduo bǎ shǒu shēnjìn [@bāo@] li.
多多把手伸进[@包@]里。</Text>
  </Paragraph>
  <Paragraph>
    <Number>28</Number>
    <StartMilliseconds>31642</StartMilliseconds>
    <EndMilliseconds>31937</EndMilliseconds>
    <Text>Duōduo bǎ shǒu shēnjìn bāo [@li@].
多多把手伸进包[@里@]。</Text>
  </Paragraph>
  <Paragraph>
    <Number>29</Number>
    <StartMilliseconds>31937</StartMilliseconds>
    <EndMilliseconds>32302</EndMilliseconds>
    <Text>Duōduo bǎ shǒu shēnjìn bāo li.
多多把手伸进包里。</Text>
  </Paragraph>
  <Paragraph>
    <Number>30</Number>
    <StartMilliseconds>32302</StartMilliseconds>
    <EndMilliseconds>32553</EndMilliseconds>
    <Text>Tā náchū jǐ kē zhǒngzi.
她拿出几颗种子。</Text>
  </Paragraph>
  <Paragraph>
    <Number>31</Number>
    <StartMilliseconds>32553</StartMilliseconds>
    <EndMilliseconds>32722</EndMilliseconds>
    <Text>[@Tā@] náchū jǐ kē zhǒngzi.
[@她@]拿出几颗种子。</Text>
  </Paragraph>
  <Paragraph>
    <Number>32</Number>
    <StartMilliseconds>32722</StartMilliseconds>
    <EndMilliseconds>33288</EndMilliseconds>
    <Text>Tā [@náchū@] jǐ kē zhǒngzi.
她[@拿出@]几颗种子。</Text>
  </Paragraph>
  <Paragraph>
    <Number>33</Number>
    <StartMilliseconds>33288</StartMilliseconds>
    <EndMilliseconds>33496</EndMilliseconds>
    <Text>Tā náchū [@jǐ@] kē zhǒngzi.
她拿出[@几@]颗种子。</Text>
  </Paragraph>
  <Paragraph>
    <Number>34</Number>
    <StartMilliseconds>33496</StartMilliseconds>
    <EndMilliseconds>33718</EndMilliseconds>
    <Text>Tā náchū jǐ [@kē@] zhǒngzi.
她拿出几[@颗@]种子。</Text>
  </Paragraph>
  <Paragraph>
    <Number>35</Number>
    <StartMilliseconds>33718</StartMilliseconds>
    <EndMilliseconds>34605</EndMilliseconds>
    <Text>Tā náchū jǐ kē [@zhǒngzi@].
她拿出几颗[@种子@]。</Text>
  </Paragraph>
  <Paragraph>
    <Number>36</Number>
    <StartMilliseconds>34605</StartMilliseconds>
    <EndMilliseconds>34788</EndMilliseconds>
    <Text>Tā náchū jǐ kē zhǒngzi.
她拿出几颗种子。</Text>
  </Paragraph>
  <Paragraph>
    <Number>37</Number>
    <StartMilliseconds>34789</StartMilliseconds>
    <EndMilliseconds>35553</EndMilliseconds>
    <Text>"Wǒ yào chóngxīn zhòng yì kē shù!"
“我要重新种一棵树！”</Text>
  </Paragraph>
  <Paragraph>
    <Number>38</Number>
    <StartMilliseconds>35554</StartMilliseconds>
    <EndMilliseconds>35735</EndMilliseconds>
    <Text>"[@Wǒ@] yào chóngxīn zhòng yì kē shù!"
“[@我@]要重新种一棵树！”</Text>
  </Paragraph>
  <Paragraph>
    <Number>39</Number>
    <StartMilliseconds>35735</StartMilliseconds>
    <EndMilliseconds>36064</EndMilliseconds>
    <Text>"Wǒ [@yào@] chóngxīn zhòng yì kē shù!"
“我[@要@]重新种一棵树！”</Text>
  </Paragraph>
  <Paragraph>
    <Number>40</Number>
    <StartMilliseconds>36064</StartMilliseconds>
    <EndMilliseconds>36565</EndMilliseconds>
    <Text>"Wǒ yào [@chóngxīn@] zhòng yì kē shù!"
“我要[@重新@]种一棵树！”</Text>
  </Paragraph>
  <Paragraph>
    <Number>41</Number>
    <StartMilliseconds>36566</StartMilliseconds>
    <EndMilliseconds>36786</EndMilliseconds>
    <Text>"Wǒ yào chóngxīn [@zhòng@] yì kē shù!"
“我要重新[@种@]一棵树！”</Text>
  </Paragraph>
  <Paragraph>
    <Number>42</Number>
    <StartMilliseconds>36786</StartMilliseconds>
    <EndMilliseconds>36936</EndMilliseconds>
    <Text>"Wǒ yào chóngxīn zhòng [@yì@] kē shù!"
“我要重新种[@一@]棵树！”</Text>
  </Paragraph>
  <Paragraph>
    <Number>43</Number>
    <StartMilliseconds>36936</StartMilliseconds>
    <EndMilliseconds>37207</EndMilliseconds>
    <Text>"Wǒ yào chóngxīn zhòng yì [@kē@] shù!"
“我要重新种一[@棵@]树！”</Text>
  </Paragraph>
  <Paragraph>
    <Number>44</Number>
    <StartMilliseconds>37208</StartMilliseconds>
    <EndMilliseconds>37586</EndMilliseconds>
    <Text>"Wǒ yào chóngxīn zhòng yì kē [@shù@]!"
“我要重新种一棵[@树@]！”</Text>
  </Paragraph>
  <Paragraph>
    <Number>45</Number>
    <StartMilliseconds>37586</StartMilliseconds>
    <EndMilliseconds>42703</EndMilliseconds>
    <Text>"Wǒ yào chóngxīn zhòng yì kē shù!"
“我要重新种一棵树！”</Text>
  </Paragraph>
  <Paragraph>
    <Number>46</Number>
    <StartMilliseconds>42703</StartMilliseconds>
    <EndMilliseconds>44608</EndMilliseconds>
    <Text>Lèle dà xiào.
乐乐大笑。</Text>
  </Paragraph>
  <Paragraph>
    <Number>47</Number>
    <StartMilliseconds>44608</StartMilliseconds>
    <EndMilliseconds>45086</EndMilliseconds>
    <Text>[@Lèle@] dà xiào.
[@乐乐@]大笑。</Text>
  </Paragraph>
  <Paragraph>
    <Number>48</Number>
    <StartMilliseconds>45086</StartMilliseconds>
    <EndMilliseconds>45416</EndMilliseconds>
    <Text>Lèle [@dà@] xiào.
乐乐[@大@]笑。</Text>
  </Paragraph>
  <Paragraph>
    <Number>49</Number>
    <StartMilliseconds>45416</StartMilliseconds>
    <EndMilliseconds>45791</EndMilliseconds>
    <Text>Lèle dà [@xiào@].
乐乐大[@笑@]。</Text>
  </Paragraph>
  <Paragraph>
    <Number>50</Number>
    <StartMilliseconds>45791</StartMilliseconds>
    <EndMilliseconds>47315</EndMilliseconds>
    <Text>Lèle dà xiào.
乐乐大笑。</Text>
  </Paragraph>
  <Paragraph>
    <Number>51</Number>
    <StartMilliseconds>47315</StartMilliseconds>
    <EndMilliseconds>48702</EndMilliseconds>
    <Text>"Duōduo, zhè bìng bù néng jiějué wèntí."
“多多，这并不能解决问题。”</Text>
  </Paragraph>
  <Paragraph>
    <Number>52</Number>
    <StartMilliseconds>48702</StartMilliseconds>
    <EndMilliseconds>49592</EndMilliseconds>
    <Text>"[@Duōduo@], zhè bìng bù néng jiějué wèntí."
“[@多多@]，这并不能解决问题。”</Text>
  </Paragraph>
  <Paragraph>
    <Number>53</Number>
    <StartMilliseconds>49592</StartMilliseconds>
    <EndMilliseconds>49802</EndMilliseconds>
    <Text>"Duōduo, [@zhè@] bìng bù néng jiějué wèntí."
“多多，[@这@]并不能解决问题。”</Text>
  </Paragraph>
  <Paragraph>
    <Number>54</Number>
    <StartMilliseconds>49802</StartMilliseconds>
    <EndMilliseconds>50052</EndMilliseconds>
    <Text>"Duōduo, zhè [@bìng@] bù néng jiějué wèntí."
“多多，这[@并@]不能解决问题。”</Text>
  </Paragraph>
  <Paragraph>
    <Number>55</Number>
    <StartMilliseconds>50052</StartMilliseconds>
    <EndMilliseconds>50322</EndMilliseconds>
    <Text>"Duōduo, zhè bìng [@bù@] néng jiějué wèntí."
“多多，这并[@不@]能解决问题。”</Text>
  </Paragraph>
  <Paragraph>
    <Number>56</Number>
    <StartMilliseconds>50322</StartMilliseconds>
    <EndMilliseconds>50589</EndMilliseconds>
    <Text>"Duōduo, zhè bìng bù [@néng@] jiějué wèntí."
“多多，这并不[@能@]解决问题。”</Text>
  </Paragraph>
  <Paragraph>
    <Number>57</Number>
    <StartMilliseconds>50589</StartMilliseconds>
    <EndMilliseconds>50890</EndMilliseconds>
    <Text>"Duōduo, zhè bìng bù néng [@jiějué@] wèntí."
“多多，这并不能[@解决@]问题。”</Text>
  </Paragraph>
  <Paragraph>
    <Number>58</Number>
    <StartMilliseconds>50890</StartMilliseconds>
    <EndMilliseconds>51900</EndMilliseconds>
    <Text>"Duōduo, zhè bìng bù néng jiějué [@wèntí@]."
“多多，这并不能解决[@问题@]。”</Text>
  </Paragraph>
  <Paragraph>
    <Number>59</Number>
    <StartMilliseconds>51901</StartMilliseconds>
    <EndMilliseconds>54088</EndMilliseconds>
    <Text>"Duōduo, zhè bìng bù néng jiějué wèntí."
“多多，这并不能解决问题。”</Text>
  </Paragraph>
  <Paragraph>
    <Number>60</Number>
    <StartMilliseconds>54088</StartMilliseconds>
    <EndMilliseconds>55130</EndMilliseconds>
    <Text>Tútu kàn shàngqu hěn shāngxīn.
涂涂看上去很伤心。</Text>
  </Paragraph>
  <Paragraph>
    <Number>61</Number>
    <StartMilliseconds>55130</StartMilliseconds>
    <EndMilliseconds>55705</EndMilliseconds>
    <Text>[@Tútu@] kàn shàngqu hěn shāngxīn.
[@涂涂@]看上去很伤心。</Text>
  </Paragraph>
  <Paragraph>
    <Number>62</Number>
    <StartMilliseconds>55705</StartMilliseconds>
    <EndMilliseconds>56004</EndMilliseconds>
    <Text>Tútu [@kàn@] shàngqu hěn shāngxīn.
涂涂[@看@]上去很伤心。</Text>
  </Paragraph>
  <Paragraph>
    <Number>63</Number>
    <StartMilliseconds>56005</StartMilliseconds>
    <EndMilliseconds>56503</EndMilliseconds>
    <Text>Tútu kàn [@shàngqu@] hěn shāngxīn.
涂涂看[@上去@]很伤心。</Text>
  </Paragraph>
  <Paragraph>
    <Number>64</Number>
    <StartMilliseconds>56503</StartMilliseconds>
    <EndMilliseconds>56767</EndMilliseconds>
    <Text>Tútu kàn shàngqu [@hěn@] shāngxīn.
涂涂看上去[@很@]伤心。</Text>
  </Paragraph>
  <Paragraph>
    <Number>65</Number>
    <StartMilliseconds>56767</StartMilliseconds>
    <EndMilliseconds>57631</EndMilliseconds>
    <Text>Tútu kàn shàngqu hěn [@shāngxīn@].
涂涂看上去很[@伤心@]。</Text>
  </Paragraph>
  <Paragraph>
    <Number>66</Number>
    <StartMilliseconds>57631</StartMilliseconds>
    <EndMilliseconds>61818</EndMilliseconds>
    <Text>Tútu kàn shàngqu hěn shāngxīn.
涂涂看上去很伤心。</Text>
  </Paragraph>
  <Paragraph>
    <Number>67</Number>
    <StartMilliseconds>61818</StartMilliseconds>
    <EndMilliseconds>63478</EndMilliseconds>
    <Text>Shāsha náqǐ shùténg.
莎莎拿起树藤。</Text>
  </Paragraph>
  <Paragraph>
    <Number>68</Number>
    <StartMilliseconds>63478</StartMilliseconds>
    <EndMilliseconds>64263</EndMilliseconds>
    <Text>[@Shāsha@] náqǐ shùténg.
[@莎莎@]拿起树藤。</Text>
  </Paragraph>
  <Paragraph>
    <Number>69</Number>
    <StartMilliseconds>64263</StartMilliseconds>
    <EndMilliseconds>64733</EndMilliseconds>
    <Text>Shāsha [@náqǐ@] shùténg.
莎莎[@拿起@]树藤。</Text>
  </Paragraph>
  <Paragraph>
    <Number>70</Number>
    <StartMilliseconds>64733</StartMilliseconds>
    <EndMilliseconds>65734</EndMilliseconds>
    <Text>Shāsha náqǐ [@shùténg@].
莎莎拿起[@树藤@]。</Text>
  </Paragraph>
  <Paragraph>
    <Number>71</Number>
    <StartMilliseconds>65735</StartMilliseconds>
    <EndMilliseconds>65960</EndMilliseconds>
    <Text>Shāsha náqǐ shùténg.
莎莎拿起树藤。</Text>
  </Paragraph>
  <Paragraph>
    <Number>72</Number>
    <StartMilliseconds>65960</StartMilliseconds>
    <EndMilliseconds>66278</EndMilliseconds>
    <Text>"Tútu,wǒmen yìqǐ yáo ba!" Tā shuō.
“涂涂，我们一起摇吧！”她说。</Text>
  </Paragraph>
  <Paragraph>
    <Number>73</Number>
    <StartMilliseconds>66278</StartMilliseconds>
    <EndMilliseconds>67135</EndMilliseconds>
    <Text>"[@Tútu@],wǒmen yìqǐ yáo ba!" Tā shuō.
“[@涂涂@]，我们一起摇吧！”她说。</Text>
  </Paragraph>
  <Paragraph>
    <Number>74</Number>
    <StartMilliseconds>67135</StartMilliseconds>
    <EndMilliseconds>67484</EndMilliseconds>
    <Text>"Tútu,[@wǒmen@] yìqǐ yáo ba!" Tā shuō.
“涂涂，[@我们@]一起摇吧！”她说。</Text>
  </Paragraph>
  <Paragraph>
    <Number>75</Number>
    <StartMilliseconds>67484</StartMilliseconds>
    <EndMilliseconds>67893</EndMilliseconds>
    <Text>"Tútu,wǒmen [@yìqǐ@] yáo ba!" Tā shuō.
“涂涂，我们[@一起@]摇吧！”她说。</Text>
  </Paragraph>
  <Paragraph>
    <Number>76</Number>
    <StartMilliseconds>67893</StartMilliseconds>
    <EndMilliseconds>68235</EndMilliseconds>
    <Text>"Tútu,wǒmen yìqǐ [@yáo@] ba!" Tā shuō.
“涂涂，我们一起[@摇@]吧！”她说。</Text>
  </Paragraph>
  <Paragraph>
    <Number>77</Number>
    <StartMilliseconds>68235</StartMilliseconds>
    <EndMilliseconds>68966</EndMilliseconds>
    <Text>"Tútu,wǒmen yìqǐ yáo [@ba@]!" Tā shuō.
“涂涂，我们一起摇[@吧@]！”她说。</Text>
  </Paragraph>
  <Paragraph>
    <Number>78</Number>
    <StartMilliseconds>68966</StartMilliseconds>
    <EndMilliseconds>69092</EndMilliseconds>
    <Text>"Tútu,wǒmen yìqǐ yáo ba!" [@Tā@] shuō.
“涂涂，我们一起摇吧！”[@她@]说。</Text>
  </Paragraph>
  <Paragraph>
    <Number>79</Number>
    <StartMilliseconds>69092</StartMilliseconds>
    <EndMilliseconds>69585</EndMilliseconds>
    <Text>"Tútu,wǒmen yìqǐ yáo ba!" Tā [@shuō@].
“涂涂，我们一起摇吧！”她[@说@]。</Text>
  </Paragraph>
  <Paragraph>
    <Number>80</Number>
    <StartMilliseconds>69585</StartMilliseconds>
    <EndMilliseconds>72058</EndMilliseconds>
    <Text>"Tútu,wǒmen yìqǐ yáo ba!" Tā shuō.
“涂涂，我们一起摇吧！”她说。</Text>
  </Paragraph>
  <Paragraph>
    <Number>81</Number>
    <StartMilliseconds>72058</StartMilliseconds>
    <EndMilliseconds>72969</EndMilliseconds>
    <Text>Shāsha hé Tútu yáozhe shùténg.
莎莎和涂涂摇着树藤。</Text>
  </Paragraph>
  <Paragraph>
    <Number>82</Number>
    <StartMilliseconds>72969</StartMilliseconds>
    <EndMilliseconds>73849</EndMilliseconds>
    <Text>[@Shāsha@] hé Tútu yáozhe shùténg.
[@莎莎@]和涂涂摇着树藤。</Text>
  </Paragraph>
  <Paragraph>
    <Number>83</Number>
    <StartMilliseconds>73849</StartMilliseconds>
    <EndMilliseconds>74062</EndMilliseconds>
    <Text>Shāsha [@hé@] Tútu yáozhe shùténg.
莎莎[@和@]涂涂摇着树藤。</Text>
  </Paragraph>
  <Paragraph>
    <Number>84</Number>
    <StartMilliseconds>74062</StartMilliseconds>
    <EndMilliseconds>74859</EndMilliseconds>
    <Text>Shāsha hé [@Tútu@] yáozhe shùténg.
莎莎和[@涂涂@]摇着树藤。</Text>
  </Paragraph>
  <Paragraph>
    <Number>85</Number>
    <StartMilliseconds>74859</StartMilliseconds>
    <EndMilliseconds>75208</EndMilliseconds>
    <Text>Shāsha hé Tútu [@yáozhe@] shùténg.
莎莎和涂涂[@摇着@]树藤。</Text>
  </Paragraph>
  <Paragraph>
    <Number>86</Number>
    <StartMilliseconds>75208</StartMilliseconds>
    <EndMilliseconds>76237</EndMilliseconds>
    <Text>Shāsha hé Tútu yáozhe [@shùténg@].
莎莎和涂涂摇着[@树藤@]。</Text>
  </Paragraph>
  <Paragraph>
    <Number>87</Number>
    <StartMilliseconds>76237</StartMilliseconds>
    <EndMilliseconds>78500</EndMilliseconds>
    <Text>Shāsha hé Tútu yáozhe shùténg.
莎莎和涂涂摇着树藤。</Text>
  </Paragraph>
  <Paragraph>
    <Number>88</Number>
    <StartMilliseconds>78500</StartMilliseconds>
    <EndMilliseconds>79487</EndMilliseconds>
    <Text>Lèle hé Duōduo kāixīn de pāi shǒu.
乐乐和多多开心地拍手。</Text>
  </Paragraph>
  <Paragraph>
    <Number>89</Number>
    <StartMilliseconds>79487</StartMilliseconds>
    <EndMilliseconds>80038</EndMilliseconds>
    <Text>[@Lèle@] hé Duōduo kāixīn de pāi shǒu.
[@乐乐@]和多多开心地拍手。</Text>
  </Paragraph>
  <Paragraph>
    <Number>90</Number>
    <StartMilliseconds>80038</StartMilliseconds>
    <EndMilliseconds>80292</EndMilliseconds>
    <Text>Lèle [@hé@] Duōduo kāixīn de pāi shǒu.
乐乐[@和@]多多开心地拍手。</Text>
  </Paragraph>
  <Paragraph>
    <Number>91</Number>
    <StartMilliseconds>80292</StartMilliseconds>
    <EndMilliseconds>81088</EndMilliseconds>
    <Text>Lèle hé [@Duōduo@] kāixīn de pāi shǒu.
乐乐和[@多多@]开心地拍手。</Text>
  </Paragraph>
  <Paragraph>
    <Number>92</Number>
    <StartMilliseconds>81088</StartMilliseconds>
    <EndMilliseconds>81583</EndMilliseconds>
    <Text>Lèle hé Duōduo [@kāixīn@] de pāi shǒu.
乐乐和多多[@开心@]地拍手。</Text>
  </Paragraph>
  <Paragraph>
    <Number>93</Number>
    <StartMilliseconds>81583</StartMilliseconds>
    <EndMilliseconds>81773</EndMilliseconds>
    <Text>Lèle hé Duōduo kāixīn [@de@] pāi shǒu.
乐乐和多多开心[@地@]拍手。</Text>
  </Paragraph>
  <Paragraph>
    <Number>94</Number>
    <StartMilliseconds>81773</StartMilliseconds>
    <EndMilliseconds>82003</EndMilliseconds>
    <Text>Lèle hé Duōduo kāixīn de [@pāi@] shǒu.
乐乐和多多开心地[@拍@]手。</Text>
  </Paragraph>
  <Paragraph>
    <Number>95</Number>
    <StartMilliseconds>82003</StartMilliseconds>
    <EndMilliseconds>82635</EndMilliseconds>
    <Text>Lèle hé Duōduo kāixīn de pāi [@shǒu@].
乐乐和多多开心地拍[@手@]。</Text>
  </Paragraph>
  <Paragraph>
    <Number>96</Number>
    <StartMilliseconds>82635</StartMilliseconds>
    <EndMilliseconds>84200</EndMilliseconds>
    <Text>Lèle hé Duōduo kāixīn de pāi shǒu.
乐乐和多多开心地拍手。</Text>
  </Paragraph>
  <Paragraph>
    <Number>97</Number>
    <StartMilliseconds>84200</StartMilliseconds>
    <EndMilliseconds>85841</EndMilliseconds>
    <Text>Lèle tiào le qǐlai.
乐乐跳了起来。</Text>
  </Paragraph>
  <Paragraph>
    <Number>98</Number>
    <StartMilliseconds>85841</StartMilliseconds>
    <EndMilliseconds>86479</EndMilliseconds>
    <Text>[@Lèle@] tiào le qǐlai.
[@乐乐@]跳了起来。</Text>
  </Paragraph>
  <Paragraph>
    <Number>99</Number>
    <StartMilliseconds>86479</StartMilliseconds>
    <EndMilliseconds>86834</EndMilliseconds>
    <Text>Lèle [@tiào@] le qǐlai.
乐乐[@跳@]了起来。</Text>
  </Paragraph>
  <Paragraph>
    <Number>100</Number>
    <StartMilliseconds>86834</StartMilliseconds>
    <EndMilliseconds>87052</EndMilliseconds>
    <Text>Lèle tiào [@le@] qǐlai.
乐乐跳[@了@]起来。</Text>
  </Paragraph>
  <Paragraph>
    <Number>101</Number>
    <StartMilliseconds>87052</StartMilliseconds>
    <EndMilliseconds>87780</EndMilliseconds>
    <Text>Lèle tiào le [@qǐlai@].
乐乐跳了[@起来@]。</Text>
  </Paragraph>
  <Paragraph>
    <Number>102</Number>
    <StartMilliseconds>87780</StartMilliseconds>
    <EndMilliseconds>89580</EndMilliseconds>
    <Text>Lèle tiào le qǐlai.
乐乐跳了起来。</Text>
  </Paragraph>
  <Paragraph>
    <Number>103</Number>
    <StartMilliseconds>89580</StartMilliseconds>
    <EndMilliseconds>90916</EndMilliseconds>
    <Text>Shùténg dǎdào le Lèle de jiǎo.
树藤打到了乐乐的脚。</Text>
  </Paragraph>
  <Paragraph>
    <Number>104</Number>
    <StartMilliseconds>90916</StartMilliseconds>
    <EndMilliseconds>91601</EndMilliseconds>
    <Text>[@Shùténg@] dǎdào le Lèle de jiǎo.
[@树藤@]打到了乐乐的脚。</Text>
  </Paragraph>
  <Paragraph>
    <Number>105</Number>
    <StartMilliseconds>91610</StartMilliseconds>
    <EndMilliseconds>92153</EndMilliseconds>
    <Text>Shùténg [@dǎdào@] le Lèle de jiǎo.
树藤[@打到@]了乐乐的脚。</Text>
  </Paragraph>
  <Paragraph>
    <Number>106</Number>
    <StartMilliseconds>92153</StartMilliseconds>
    <EndMilliseconds>92519</EndMilliseconds>
    <Text>Shùténg dǎdào [@le@] Lèle de jiǎo.
树藤打到[@了@]乐乐的脚。</Text>
  </Paragraph>
  <Paragraph>
    <Number>107</Number>
    <StartMilliseconds>92518</StartMilliseconds>
    <EndMilliseconds>92799</EndMilliseconds>
    <Text>Shùténg dǎdào le [@Lèle@] de jiǎo.
树藤打到了[@乐乐@]的脚。</Text>
  </Paragraph>
  <Paragraph>
    <Number>108</Number>
    <StartMilliseconds>92800</StartMilliseconds>
    <EndMilliseconds>93002</EndMilliseconds>
    <Text>Shùténg dǎdào le Lèle [@de@] jiǎo.
树藤打到了乐乐[@的@]脚。</Text>
  </Paragraph>
  <Paragraph>
    <Number>109</Number>
    <StartMilliseconds>93002</StartMilliseconds>
    <EndMilliseconds>93651</EndMilliseconds>
    <Text>Shùténg dǎdào le Lèle de [@jiǎo@].
树藤打到了乐乐的[@脚@]。</Text>
  </Paragraph>
  <Paragraph>
    <Number>110</Number>
    <StartMilliseconds>93652</StartMilliseconds>
    <EndMilliseconds>93966</EndMilliseconds>
    <Text>Shùténg dǎdào le Lèle de jiǎo.
树藤打到了乐乐的脚。</Text>
  </Paragraph>
  <Paragraph>
    <Number>111</Number>
    <StartMilliseconds>93966</StartMilliseconds>
    <EndMilliseconds>94341</EndMilliseconds>
    <Text>"Ò!" Lèle dà xiào.
“哦！”乐乐大笑。</Text>
  </Paragraph>
  <Paragraph>
    <Number>112</Number>
    <StartMilliseconds>94341</StartMilliseconds>
    <EndMilliseconds>95109</EndMilliseconds>
    <Text>"[@Ò@]!" Lèle dà xiào.
“[@哦@]！”乐乐大笑。</Text>
  </Paragraph>
  <Paragraph>
    <Number>113</Number>
    <StartMilliseconds>95109</StartMilliseconds>
    <EndMilliseconds>96682</EndMilliseconds>
    <Text>"Ò!" Lèle dà xiào.
“哦！”乐乐大笑。</Text>
  </Paragraph>
  <Paragraph>
    <Number>114</Number>
    <StartMilliseconds>96682</StartMilliseconds>
    <EndMilliseconds>97201</EndMilliseconds>
    <Text>"Ò!" [@Lèle@] dà xiào.
“哦！”[@乐乐@]大笑。</Text>
  </Paragraph>
  <Paragraph>
    <Number>115</Number>
    <StartMilliseconds>97201</StartMilliseconds>
    <EndMilliseconds>97505</EndMilliseconds>
    <Text>"Ò!" Lèle [@dà@] xiào.
“哦！”乐乐[@大@]笑。</Text>
  </Paragraph>
  <Paragraph>
    <Number>116</Number>
    <StartMilliseconds>97505</StartMilliseconds>
    <EndMilliseconds>98002</EndMilliseconds>
    <Text>"Ò!" Lèle dà [@xiào@].
“哦！”乐乐大[@笑@]。</Text>
  </Paragraph>
  <Paragraph>
    <Number>117</Number>
    <StartMilliseconds>98002</StartMilliseconds>
    <EndMilliseconds>98754</EndMilliseconds>
    <Text>"Ò!" Lèle dà xiào.
“哦！”乐乐大笑。</Text>
  </Paragraph>
  <Paragraph>
    <Number>118</Number>
    <StartMilliseconds>98754</StartMilliseconds>
    <EndMilliseconds>99370</EndMilliseconds>
    <Text>Jiēzhe, Duōduo tiào.
接着，多多跳。</Text>
  </Paragraph>
  <Paragraph>
    <Number>119</Number>
    <StartMilliseconds>99370</StartMilliseconds>
    <EndMilliseconds>100298</EndMilliseconds>
    <Text>[@Jiēzhe@], Duōduo tiào.
[@接着@]，多多跳。</Text>
  </Paragraph>
  <Paragraph>
    <Number>120</Number>
    <StartMilliseconds>100298</StartMilliseconds>
    <EndMilliseconds>100652</EndMilliseconds>
    <Text>Jiēzhe, [@Duōduo@] tiào.
接着，[@多多@]跳。</Text>
  </Paragraph>
  <Paragraph>
    <Number>121</Number>
    <StartMilliseconds>100652</StartMilliseconds>
    <EndMilliseconds>101154</EndMilliseconds>
    <Text>Jiēzhe, Duōduo [@tiào@].
接着，多多[@跳@]。</Text>
  </Paragraph>
  <Paragraph>
    <Number>122</Number>
    <StartMilliseconds>101154</StartMilliseconds>
    <EndMilliseconds>103786</EndMilliseconds>
    <Text>Jiēzhe, Duōduo tiào.
接着，多多跳。</Text>
  </Paragraph>
  <Paragraph>
    <Number>123</Number>
    <StartMilliseconds>103786</StartMilliseconds>
    <EndMilliseconds>107519</EndMilliseconds>
    <Text>Tútu xiǎng zài tiào yí cì.
涂涂想再跳一次。</Text>
  </Paragraph>
  <Paragraph>
    <Number>124</Number>
    <StartMilliseconds>107519</StartMilliseconds>
    <EndMilliseconds>108152</EndMilliseconds>
    <Text>[@Tútu@] xiǎng zài tiào yí cì.
[@涂涂@]想再跳一次。</Text>
  </Paragraph>
  <Paragraph>
    <Number>125</Number>
    <StartMilliseconds>108152</StartMilliseconds>
    <EndMilliseconds>108402</EndMilliseconds>
    <Text>Tútu [@xiǎng@] zài tiào yí cì.
涂涂[@想@]再跳一次。</Text>
  </Paragraph>
  <Paragraph>
    <Number>126</Number>
    <StartMilliseconds>108402</StartMilliseconds>
    <EndMilliseconds>108708</EndMilliseconds>
    <Text>Tútu xiǎng [@zài@] tiào yí cì.
涂涂想[@再@]跳一次。</Text>
  </Paragraph>
  <Paragraph>
    <Number>127</Number>
    <StartMilliseconds>108708</StartMilliseconds>
    <EndMilliseconds>108951</EndMilliseconds>
    <Text>Tútu xiǎng zài [@tiào@] yí cì.
涂涂想再[@跳@]一次。</Text>
  </Paragraph>
  <Paragraph>
    <Number>128</Number>
    <StartMilliseconds>108951</StartMilliseconds>
    <EndMilliseconds>109202</EndMilliseconds>
    <Text>Tútu xiǎng zài tiào [@yí@] cì.
涂涂想再跳[@一@]次。</Text>
  </Paragraph>
  <Paragraph>
    <Number>129</Number>
    <StartMilliseconds>109202</StartMilliseconds>
    <EndMilliseconds>109702</EndMilliseconds>
    <Text>Tútu xiǎng zài tiào yí [@cì@].
涂涂想再跳一[@次@]。</Text>
  </Paragraph>
  <Paragraph>
    <Number>130</Number>
    <StartMilliseconds>109702</StartMilliseconds>
    <EndMilliseconds>111610</EndMilliseconds>
    <Text>Tútu xiǎng zài tiào yí cì.
涂涂想再跳一次。</Text>
  </Paragraph>
  <Paragraph>
    <Number>131</Number>
    <StartMilliseconds>111610</StartMilliseconds>
    <EndMilliseconds>112943</EndMilliseconds>
    <Text>Lèle hé Shāsha yìqǐ yáo shùténg.
乐乐和莎莎一起摇树藤。</Text>
  </Paragraph>
  <Paragraph>
    <Number>132</Number>
    <StartMilliseconds>112943</StartMilliseconds>
    <EndMilliseconds>113542</EndMilliseconds>
    <Text>[@Lèle@] hé Shāsha yìqǐ yáo shùténg.
[@乐乐@]和莎莎一起摇树藤。</Text>
  </Paragraph>
  <Paragraph>
    <Number>133</Number>
    <StartMilliseconds>113542</StartMilliseconds>
    <EndMilliseconds>113780</EndMilliseconds>
    <Text>Lèle [@hé@] Shāsha yìqǐ yáo shùténg.
乐乐[@和@]莎莎一起摇树藤。</Text>
  </Paragraph>
  <Paragraph>
    <Number>134</Number>
    <StartMilliseconds>113780</StartMilliseconds>
    <EndMilliseconds>114619</EndMilliseconds>
    <Text>Lèle hé [@Shāsha@] yìqǐ yáo shùténg.
乐乐和[@莎莎@]一起摇树藤。</Text>
  </Paragraph>
  <Paragraph>
    <Number>135</Number>
    <StartMilliseconds>114619</StartMilliseconds>
    <EndMilliseconds>115105</EndMilliseconds>
    <Text>Lèle hé Shāsha [@yìqǐ@] yáo shùténg.
乐乐和莎莎[@一起@]摇树藤。</Text>
  </Paragraph>
  <Paragraph>
    <Number>136</Number>
    <StartMilliseconds>115105</StartMilliseconds>
    <EndMilliseconds>115351</EndMilliseconds>
    <Text>Lèle hé Shāsha yìqǐ [@yáo@] shùténg.
乐乐和莎莎一起[@摇@]树藤。</Text>
  </Paragraph>
  <Paragraph>
    <Number>137</Number>
    <StartMilliseconds>115351</StartMilliseconds>
    <EndMilliseconds>116104</EndMilliseconds>
    <Text>Lèle hé Shāsha yìqǐ yáo [@shùténg@].
乐乐和莎莎一起摇[@树藤@]。</Text>
  </Paragraph>
  <Paragraph>
    <Number>138</Number>
    <StartMilliseconds>116104</StartMilliseconds>
    <EndMilliseconds>119041</EndMilliseconds>
    <Text>Lèle hé Shāsha yìqǐ yáo shùténg.
乐乐和莎莎一起摇树藤。</Text>
  </Paragraph>
  <Paragraph>
    <Number>139</Number>
    <StartMilliseconds>119041</StartMilliseconds>
    <EndMilliseconds>120682</EndMilliseconds>
    <Text>Tútu zhuāzhe tā de wěiba tiào.
涂涂抓着他的尾巴跳。</Text>
  </Paragraph>
  <Paragraph>
    <Number>140</Number>
    <StartMilliseconds>120682</StartMilliseconds>
    <EndMilliseconds>121253</EndMilliseconds>
    <Text>[@Tútu@] zhuāzhe tā de wěiba tiào.
[@涂涂@]抓着他的尾巴跳。</Text>
  </Paragraph>
  <Paragraph>
    <Number>141</Number>
    <StartMilliseconds>121253</StartMilliseconds>
    <EndMilliseconds>121791</EndMilliseconds>
    <Text>Tútu [@zhuāzhe@] tā de wěiba tiào.
涂涂[@抓着@]他的尾巴跳。</Text>
  </Paragraph>
  <Paragraph>
    <Number>142</Number>
    <StartMilliseconds>121791</StartMilliseconds>
    <EndMilliseconds>122003</EndMilliseconds>
    <Text>Tútu zhuāzhe [@tā@] de wěiba tiào.
涂涂抓着[@他@]的尾巴跳。</Text>
  </Paragraph>
  <Paragraph>
    <Number>143</Number>
    <StartMilliseconds>122003</StartMilliseconds>
    <EndMilliseconds>122253</EndMilliseconds>
    <Text>Tútu zhuāzhe tā [@de@] wěiba tiào.
涂涂抓着他[@的@]尾巴跳。</Text>
  </Paragraph>
  <Paragraph>
    <Number>144</Number>
    <StartMilliseconds>122253</StartMilliseconds>
    <EndMilliseconds>122630</EndMilliseconds>
    <Text>Tútu zhuāzhe tā de [@wěiba@] tiào.
涂涂抓着他的[@尾巴@]跳。</Text>
  </Paragraph>
  <Paragraph>
    <Number>145</Number>
    <StartMilliseconds>122629</StartMilliseconds>
    <EndMilliseconds>122931</EndMilliseconds>
    <Text>Tútu zhuāzhe tā de wěiba [@tiào@].
涂涂抓着他的尾巴[@跳@]。</Text>
  </Paragraph>
  <Paragraph>
    <Number>146</Number>
    <StartMilliseconds>122932</StartMilliseconds>
    <EndMilliseconds>123197</EndMilliseconds>
    <Text>Tútu zhuāzhe tā de wěiba tiào.
涂涂抓着他的尾巴跳。</Text>
  </Paragraph>
  <Paragraph>
    <Number>147</Number>
    <StartMilliseconds>123197</StartMilliseconds>
    <EndMilliseconds>123591</EndMilliseconds>
    <Text>"Yē!" Tā shuō.
“耶！”他说。</Text>
  </Paragraph>
  <Paragraph>
    <Number>148</Number>
    <StartMilliseconds>123591</StartMilliseconds>
    <EndMilliseconds>124982</EndMilliseconds>
    <Text>"[@Yē@]!" Tā shuō.
“[@耶@]！”他说。</Text>
  </Paragraph>
  <Paragraph>
    <Number>149</Number>
    <StartMilliseconds>124982</StartMilliseconds>
    <EndMilliseconds>125284</EndMilliseconds>
    <Text>"Yē!" [@Tā@] shuō.
“耶！”[@他@]说。</Text>
  </Paragraph>
  <Paragraph>
    <Number>150</Number>
    <StartMilliseconds>125284</StartMilliseconds>
    <EndMilliseconds>125788</EndMilliseconds>
    <Text>"Yē!" Tā [@shuō@].
“耶！”他[@说@]。</Text>
  </Paragraph>
  <Paragraph>
    <Number>151</Number>
    <StartMilliseconds>125788</StartMilliseconds>
    <EndMilliseconds>126318</EndMilliseconds>
    <Text>"Yē!" Tā shuō.
“耶！”他说。</Text>
  </Paragraph>
  <Paragraph>
    <Number>152</Number>
    <StartMilliseconds>126318</StartMilliseconds>
    <EndMilliseconds>126718</EndMilliseconds>
    <Text>"Zhè tài hǎowánr le!" Tútu shuō.
“这太好玩儿了！”涂涂说。</Text>
  </Paragraph>
  <Paragraph>
    <Number>153</Number>
    <StartMilliseconds>126718</StartMilliseconds>
    <EndMilliseconds>127021</EndMilliseconds>
    <Text>"[@Zhè@] tài hǎowánr le!" Tútu shuō.
“[@这@]太好玩儿了！”涂涂说。</Text>
  </Paragraph>
  <Paragraph>
    <Number>154</Number>
    <StartMilliseconds>127021</StartMilliseconds>
    <EndMilliseconds>127419</EndMilliseconds>
    <Text>"Zhè [@tài@] hǎowánr le!" Tútu shuō.
“这[@太@]好玩儿了！”涂涂说。</Text>
  </Paragraph>
  <Paragraph>
    <Number>155</Number>
    <StartMilliseconds>127419</StartMilliseconds>
    <EndMilliseconds>128020</EndMilliseconds>
    <Text>"Zhè tài [@hǎowánr@] le!" Tútu shuō.
“这太[@好玩儿@]了！”涂涂说。</Text>
  </Paragraph>
  <Paragraph>
    <Number>156</Number>
    <StartMilliseconds>128020</StartMilliseconds>
    <EndMilliseconds>128704</EndMilliseconds>
    <Text>"Zhè tài hǎowánr [@le@]!" Tútu shuō.
“这太好玩儿[@了@]！”涂涂说。</Text>
  </Paragraph>
  <Paragraph>
    <Number>157</Number>
    <StartMilliseconds>128705</StartMilliseconds>
    <EndMilliseconds>129063</EndMilliseconds>
    <Text>"Zhè tài hǎowánr le!" [@Tútu@] shuō.
“这太好玩儿了！”[@涂涂@]说。</Text>
  </Paragraph>
  <Paragraph>
    <Number>158</Number>
    <StartMilliseconds>129063</StartMilliseconds>
    <EndMilliseconds>129504</EndMilliseconds>
    <Text>"Zhè tài hǎowánr le!" Tútu [@shuō@].
“这太好玩儿了！”涂涂[@说@]。</Text>
  </Paragraph>
  <Paragraph>
    <Number>159</Number>
    <StartMilliseconds>129504</StartMilliseconds>
    <EndMilliseconds>130183</EndMilliseconds>
    <Text>"Zhè tài hǎowánr le!" Tútu shuō.
“这太好玩儿了！”涂涂说。</Text>
  </Paragraph>
  <Paragraph>
    <Number>160</Number>
    <StartMilliseconds>130183</StartMilliseconds>
    <EndMilliseconds>130710</EndMilliseconds>
    <Text>Tā wàng le zìjǐ zhuāzhe wěiba.
他忘了自己抓着尾巴。</Text>
  </Paragraph>
  <Paragraph>
    <Number>161</Number>
    <StartMilliseconds>130710</StartMilliseconds>
    <EndMilliseconds>130962</EndMilliseconds>
    <Text>[@Tā@] wàng le zìjǐ zhuāzhe wěiba.
[@他@]忘了自己抓着尾巴。</Text>
  </Paragraph>
  <Paragraph>
    <Number>162</Number>
    <StartMilliseconds>130962</StartMilliseconds>
    <EndMilliseconds>131175</EndMilliseconds>
    <Text>Tā [@wàng@] le zìjǐ zhuāzhe wěiba.
他[@忘@]了自己抓着尾巴。</Text>
  </Paragraph>
  <Paragraph>
    <Number>163</Number>
    <StartMilliseconds>131175</StartMilliseconds>
    <EndMilliseconds>131475</EndMilliseconds>
    <Text>Tā wàng [@le@] zìjǐ zhuāzhe wěiba.
他忘[@了@]自己抓着尾巴。</Text>
  </Paragraph>
  <Paragraph>
    <Number>164</Number>
    <StartMilliseconds>131475</StartMilliseconds>
    <EndMilliseconds>131934</EndMilliseconds>
    <Text>Tā wàng le [@zìjǐ@] zhuāzhe wěiba.
他忘了[@自己@]抓着尾巴。</Text>
  </Paragraph>
  <Paragraph>
    <Number>165</Number>
    <StartMilliseconds>131935</StartMilliseconds>
    <EndMilliseconds>132358</EndMilliseconds>
    <Text>Tā wàng le zìjǐ [@zhuāzhe@] wěiba.
他忘了自己[@抓着@]尾巴。</Text>
  </Paragraph>
  <Paragraph>
    <Number>166</Number>
    <StartMilliseconds>132358</StartMilliseconds>
    <EndMilliseconds>132998</EndMilliseconds>
    <Text>Tā wàng le zìjǐ zhuāzhe [@wěiba@].
他忘了自己抓着[@尾巴@]。</Text>
  </Paragraph>
  <Paragraph>
    <Number>167</Number>
    <StartMilliseconds>132999</StartMilliseconds>
    <EndMilliseconds>133355</EndMilliseconds>
    <Text>Tā wàng le zìjǐ zhuāzhe wěiba.
他忘了自己抓着尾巴。</Text>
  </Paragraph>
  <Paragraph>
    <Number>168</Number>
    <StartMilliseconds>133355</StartMilliseconds>
    <EndMilliseconds>133758</EndMilliseconds>
    <Text>Tā sōngkāi le shǒu. 
他松开了手。</Text>
  </Paragraph>
  <Paragraph>
    <Number>169</Number>
    <StartMilliseconds>133758</StartMilliseconds>
    <EndMilliseconds>134139</EndMilliseconds>
    <Text>[@Tā@] sōngkāi le shǒu. 
[@他@]松开了手。</Text>
  </Paragraph>
  <Paragraph>
    <Number>170</Number>
    <StartMilliseconds>134139</StartMilliseconds>
    <EndMilliseconds>134755</EndMilliseconds>
    <Text>Tā [@sōngkāi@] le shǒu. 
他[@松开@]了手。</Text>
  </Paragraph>
  <Paragraph>
    <Number>171</Number>
    <StartMilliseconds>134755</StartMilliseconds>
    <EndMilliseconds>134935</EndMilliseconds>
    <Text>Tā sōngkāi [@le@] shǒu. 
他松开[@了@]手。</Text>
  </Paragraph>
  <Paragraph>
    <Number>172</Number>
    <StartMilliseconds>134935</StartMilliseconds>
    <EndMilliseconds>135537</EndMilliseconds>
    <Text>Tā sōngkāi le [@shǒu@]. 
他松开了[@手@]。</Text>
  </Paragraph>
  <Paragraph>
    <Number>173</Number>
    <StartMilliseconds>135538</StartMilliseconds>
    <EndMilliseconds>135620</EndMilliseconds>
    <Text>Tā sōngkāi le shǒu. 
他松开了手。</Text>
  </Paragraph>
  <Paragraph>
    <Number>174</Number>
    <StartMilliseconds>135620</StartMilliseconds>
    <EndMilliseconds>135830</EndMilliseconds>
    <Text>Tútu de wěiba kāishǐ huàngdòng.
涂涂的尾巴开始晃动。</Text>
  </Paragraph>
  <Paragraph>
    <Number>175</Number>
    <StartMilliseconds>135831</StartMilliseconds>
    <EndMilliseconds>136041</EndMilliseconds>
    <Text>[@Tútu@] de wěiba kāishǐ huàngdòng.
[@涂涂@]的尾巴开始晃动。</Text>
  </Paragraph>
  <Paragraph>
    <Number>176</Number>
    <StartMilliseconds>136041</StartMilliseconds>
    <EndMilliseconds>136224</EndMilliseconds>
    <Text>Tútu [@de@] wěiba kāishǐ huàngdòng.
涂涂[@的@]尾巴开始晃动。</Text>
  </Paragraph>
  <Paragraph>
    <Number>177</Number>
    <StartMilliseconds>136224</StartMilliseconds>
    <EndMilliseconds>137037</EndMilliseconds>
    <Text>Tútu de [@wěiba@] kāishǐ huàngdòng.
涂涂的[@尾巴@]开始晃动。</Text>
  </Paragraph>
  <Paragraph>
    <Number>178</Number>
    <StartMilliseconds>137037</StartMilliseconds>
    <EndMilliseconds>137586</EndMilliseconds>
    <Text>Tútu de wěiba [@kāishǐ@] huàngdòng.
涂涂的尾巴[@开始@]晃动。</Text>
  </Paragraph>
  <Paragraph>
    <Number>179</Number>
    <StartMilliseconds>137586</StartMilliseconds>
    <EndMilliseconds>138088</EndMilliseconds>
    <Text>Tútu de wěiba kāishǐ [@huàngdòng@].
涂涂的尾巴开始[@晃动@]。</Text>
  </Paragraph>
  <Paragraph>
    <Number>180</Number>
    <StartMilliseconds>138088</StartMilliseconds>
    <EndMilliseconds>138440</EndMilliseconds>
    <Text>Tútu de wěiba kāishǐ huàngdòng.
涂涂的尾巴开始晃动。</Text>
  </Paragraph>
  <Paragraph>
    <Number>181</Number>
    <StartMilliseconds>138440</StartMilliseconds>
    <EndMilliseconds>138672</EndMilliseconds>
    <Text>"Shùténg!" Duōduo shuō,
“树藤！”多多说，</Text>
  </Paragraph>
  <Paragraph>
    <Number>182</Number>
    <StartMilliseconds>138672</StartMilliseconds>
    <EndMilliseconds>139855</EndMilliseconds>
    <Text>"[@Shùténg@]!" Duōduo shuō,
“[@树藤@]！”多多说，</Text>
  </Paragraph>
  <Paragraph>
    <Number>183</Number>
    <StartMilliseconds>139855</StartMilliseconds>
    <EndMilliseconds>140339</EndMilliseconds>
    <Text>"Shùténg!" [@Duōduo@] shuō,
“树藤！”[@多多@]说，</Text>
  </Paragraph>
  <Paragraph>
    <Number>184</Number>
    <StartMilliseconds>140339</StartMilliseconds>
    <EndMilliseconds>140835</EndMilliseconds>
    <Text>"Shùténg!" Duōduo [@shuō@],
“树藤！”多多[@说@]，</Text>
  </Paragraph>
  <Paragraph>
    <Number>185</Number>
    <StartMilliseconds>140835</StartMilliseconds>
    <EndMilliseconds>141146</EndMilliseconds>
    <Text>"Shùténg!" Duōduo shuō,
“树藤！”多多说，</Text>
  </Paragraph>
  <Paragraph>
    <Number>186</Number>
    <StartMilliseconds>141146</StartMilliseconds>
    <EndMilliseconds>141730</EndMilliseconds>
    <Text>"Yòu chánzài yìqǐ le!"
“又缠在一起了！”</Text>
  </Paragraph>
  <Paragraph>
    <Number>187</Number>
    <StartMilliseconds>141730</StartMilliseconds>
    <EndMilliseconds>142155</EndMilliseconds>
    <Text>"[@Yòu@] chánzài yìqǐ le!"
“[@又@]缠在一起了！”</Text>
  </Paragraph>
  <Paragraph>
    <Number>188</Number>
    <StartMilliseconds>142155</StartMilliseconds>
    <EndMilliseconds>142742</EndMilliseconds>
    <Text>"Yòu [@chánzài@] yìqǐ le!"
“又[@缠在@]一起了！”</Text>
  </Paragraph>
  <Paragraph>
    <Number>189</Number>
    <StartMilliseconds>142743</StartMilliseconds>
    <EndMilliseconds>143202</EndMilliseconds>
    <Text>"Yòu chánzài [@yìqǐ@] le!"
“又缠在[@一起@]了！”</Text>
  </Paragraph>
  <Paragraph>
    <Number>190</Number>
    <StartMilliseconds>143202</StartMilliseconds>
    <EndMilliseconds>143699</EndMilliseconds>
    <Text>"Yòu chánzài yìqǐ [@le@]!"
“又缠在一起[@了@]！”</Text>
  </Paragraph>
  <Paragraph>
    <Number>191</Number>
    <StartMilliseconds>143705</StartMilliseconds>
    <EndMilliseconds>148952</EndMilliseconds>
    <Text>"Yòu chánzài yìqǐ le!"
“又缠在一起了！”</Text>
  </Paragraph>
  <Paragraph>
    <Number>192</Number>
    <StartMilliseconds>148953</StartMilliseconds>
    <EndMilliseconds>150236</EndMilliseconds>
    <Text>Lèle dà xiào.
乐乐大笑。</Text>
  </Paragraph>
  <Paragraph>
    <Number>193</Number>
    <StartMilliseconds>150236</StartMilliseconds>
    <EndMilliseconds>150878</EndMilliseconds>
    <Text>[@Lèle@] dà xiào.
[@乐乐@]大笑。</Text>
  </Paragraph>
  <Paragraph>
    <Number>194</Number>
    <StartMilliseconds>150878</StartMilliseconds>
    <EndMilliseconds>151100</EndMilliseconds>
    <Text>Lèle [@dà@] xiào.
乐乐[@大@]笑。</Text>
  </Paragraph>
  <Paragraph>
    <Number>195</Number>
    <StartMilliseconds>151100</StartMilliseconds>
    <EndMilliseconds>151516</EndMilliseconds>
    <Text>Lèle dà [@xiào@].
乐乐大[@笑@]。</Text>
  </Paragraph>
  <Paragraph>
    <Number>196</Number>
    <StartMilliseconds>151516</StartMilliseconds>
    <EndMilliseconds>153870</EndMilliseconds>
    <Text>Lèle dà xiào.
乐乐大笑。</Text>
  </Paragraph>
  <Paragraph>
    <Number>197</Number>
    <StartMilliseconds>153870</StartMilliseconds>
    <EndMilliseconds>154403</EndMilliseconds>
    <Text>"Méi guānxi.
“没关系。</Text>
  </Paragraph>
  <Paragraph>
    <Number>198</Number>
    <StartMilliseconds>154403</StartMilliseconds>
    <EndMilliseconds>154726</EndMilliseconds>
    <Text>"[@Méi@] guānxi.
“[@没@]关系。</Text>
  </Paragraph>
  <Paragraph>
    <Number>199</Number>
    <StartMilliseconds>154726</StartMilliseconds>
    <EndMilliseconds>155571</EndMilliseconds>
    <Text>"Méi [@guānxi@].
“没[@关系@]。</Text>
  </Paragraph>
  <Paragraph>
    <Number>200</Number>
    <StartMilliseconds>155571</StartMilliseconds>
    <EndMilliseconds>155593</EndMilliseconds>
    <Text>"Méi guānxi.
“没关系。</Text>
  </Paragraph>
  <Paragraph>
    <Number>201</Number>
    <StartMilliseconds>155593</StartMilliseconds>
    <EndMilliseconds>155647</EndMilliseconds>
    <Text>Wánr de kāixīn jiù hǎo!"
玩儿得开心就好！”</Text>
  </Paragraph>
  <Paragraph>
    <Number>202</Number>
    <StartMilliseconds>155647</StartMilliseconds>
    <EndMilliseconds>155995</EndMilliseconds>
    <Text>[@Wánr@] de kāixīn jiù hǎo!"
[@玩儿@]得开心就好！”</Text>
  </Paragraph>
  <Paragraph>
    <Number>203</Number>
    <StartMilliseconds>155995</StartMilliseconds>
    <EndMilliseconds>156218</EndMilliseconds>
    <Text>Wánr [@de@] kāixīn jiù hǎo!"
玩儿[@得@]开心就好！”</Text>
  </Paragraph>
  <Paragraph>
    <Number>204</Number>
    <StartMilliseconds>156206</StartMilliseconds>
    <EndMilliseconds>156791</EndMilliseconds>
    <Text>Wánr de [@kāixīn@] jiù hǎo!"
玩儿得[@开心@]就好！”</Text>
  </Paragraph>
  <Paragraph>
    <Number>205</Number>
    <StartMilliseconds>156791</StartMilliseconds>
    <EndMilliseconds>156997</EndMilliseconds>
    <Text>Wánr de kāixīn [@jiù@] hǎo!"
玩儿得开心[@就@]好！”</Text>
  </Paragraph>
  <Paragraph>
    <Number>206</Number>
    <StartMilliseconds>156997</StartMilliseconds>
    <EndMilliseconds>157970</EndMilliseconds>
    <Text>Wánr de kāixīn jiù [@hǎo@]!"
玩儿得开心就[@好@]！”</Text>
  </Paragraph>
  <Paragraph>
    <Number>207</Number>
    <StartMilliseconds>157970</StartMilliseconds>
    <EndMilliseconds>161469</EndMilliseconds>
    <Text>Wánr de kāixīn jiù hǎo!"
玩儿得开心就好！”</Text>
  </Paragraph>
</Subtitle>